{
"meta":{"test_sets":[],"test_metrics":[],"learn_metrics":[{"best_value":"Min","name":"RMSE"}],"launch_mode":"Train","parameters":"","iteration_count":1000,"learn_sets":["learn"],"name":"experiment"},
"iterations":[
{"learn":[14.61268541],"iteration":0,"passed_time":0.1253583951,"remaining_time":125.2330367},
{"learn":[14.23196558],"iteration":1,"passed_time":0.1260577212,"remaining_time":62.9028029},
{"learn":[13.86674177],"iteration":2,"passed_time":0.1267768005,"remaining_time":42.1321567},
{"learn":[13.49946468],"iteration":3,"passed_time":0.1274837733,"remaining_time":31.74345956},
{"learn":[13.16661202],"iteration":4,"passed_time":0.1281867274,"remaining_time":25.50915875},
{"learn":[12.85632158],"iteration":5,"passed_time":0.1289098555,"remaining_time":21.35606606},
{"learn":[12.56784336],"iteration":6,"passed_time":0.1296760676,"remaining_time":18.39547644},
{"learn":[12.31617801],"iteration":7,"passed_time":0.130503593,"remaining_time":16.18244553},
{"learn":[12.01509946],"iteration":8,"passed_time":0.1313103937,"remaining_time":14.45873335},
{"learn":[11.71512571],"iteration":9,"passed_time":0.1320789203,"remaining_time":13.07581311},
{"learn":[11.43264457],"iteration":10,"passed_time":0.1328139344,"remaining_time":11.9411801},
{"learn":[11.17973129],"iteration":11,"passed_time":0.1335639105,"remaining_time":10.99676197},
{"learn":[10.93746433],"iteration":12,"passed_time":0.1343081046,"remaining_time":10.19708456},
{"learn":[10.69387075],"iteration":13,"passed_time":0.1351953107,"remaining_time":9.521612599},
{"learn":[10.4615922],"iteration":14,"passed_time":0.1359307156,"remaining_time":8.926116992},
{"learn":[10.2299235],"iteration":15,"passed_time":0.1366848814,"remaining_time":8.406120208},
{"learn":[10.01419731],"iteration":16,"passed_time":0.1374594919,"remaining_time":7.948392971},
{"learn":[9.795856918],"iteration":17,"passed_time":0.1382237798,"remaining_time":7.540875097},
{"learn":[9.60040151],"iteration":18,"passed_time":0.1390938681,"remaining_time":7.181636031},
{"learn":[9.418664989],"iteration":19,"passed_time":0.1400022905,"remaining_time":6.860112236},
{"learn":[9.249278645],"iteration":20,"passed_time":0.1410182472,"remaining_time":6.574136379},
{"learn":[9.090113396],"iteration":21,"passed_time":0.1421261419,"remaining_time":6.318153036},
{"learn":[8.909548708],"iteration":22,"passed_time":0.1429513027,"remaining_time":6.072322726},
{"learn":[8.740140208],"iteration":23,"passed_time":0.1441819082,"remaining_time":5.863397601},
{"learn":[8.59377682],"iteration":24,"passed_time":0.1452676226,"remaining_time":5.665437281},
{"learn":[8.453885414],"iteration":25,"passed_time":0.146139595,"remaining_time":5.474614059},
{"learn":[8.317732234],"iteration":26,"passed_time":0.146975178,"remaining_time":5.296549933},
{"learn":[8.180896085],"iteration":27,"passed_time":0.1478693488,"remaining_time":5.133178824},
{"learn":[8.053220863],"iteration":28,"passed_time":0.1487959104,"remaining_time":4.982097551},
{"learn":[7.924234474],"iteration":29,"passed_time":0.1496907732,"remaining_time":4.840001668},
{"learn":[7.818879511],"iteration":30,"passed_time":0.1506883503,"remaining_time":4.710226174},
{"learn":[7.719346395],"iteration":31,"passed_time":0.1516044896,"remaining_time":4.586035809},
{"learn":[7.624163594],"iteration":32,"passed_time":0.1528342232,"remaining_time":4.478505874},
{"learn":[7.524952543],"iteration":33,"passed_time":0.1538681295,"remaining_time":4.371665091},
{"learn":[7.424464745],"iteration":34,"passed_time":0.1547863433,"remaining_time":4.267680609},
{"learn":[7.327482321],"iteration":35,"passed_time":0.1556873396,"remaining_time":4.168960982},
{"learn":[7.238666841],"iteration":36,"passed_time":0.1567615238,"remaining_time":4.080036416},
{"learn":[7.158842395],"iteration":37,"passed_time":0.1578215851,"remaining_time":3.995378024},
{"learn":[7.074348246],"iteration":38,"passed_time":0.1586921249,"remaining_time":3.910336719},
{"learn":[6.992269093],"iteration":39,"passed_time":0.1595769258,"remaining_time":3.82984622},
{"learn":[6.925219745],"iteration":40,"passed_time":0.1605074866,"remaining_time":3.75430926},
{"learn":[6.86013671],"iteration":41,"passed_time":0.1671918439,"remaining_time":3.813566344},
{"learn":[6.786739622],"iteration":42,"passed_time":0.1680956357,"remaining_time":3.741105195},
{"learn":[6.73057926],"iteration":43,"passed_time":0.1689412411,"remaining_time":3.67063242},
{"learn":[6.666356486],"iteration":44,"passed_time":0.1697681457,"remaining_time":3.602857314},
{"learn":[6.606182832],"iteration":45,"passed_time":0.1707432536,"remaining_time":3.541066608},
{"learn":[6.547854615],"iteration":46,"passed_time":0.1717859396,"remaining_time":3.483234052},
{"learn":[6.49240675],"iteration":47,"passed_time":0.1726593657,"remaining_time":3.424410753},
{"learn":[6.431317261],"iteration":48,"passed_time":0.1735195128,"remaining_time":3.367695034},
{"learn":[6.377586395],"iteration":49,"passed_time":0.174493578,"remaining_time":3.315377982},
{"learn":[6.327558015],"iteration":50,"passed_time":0.1754892604,"remaining_time":3.265476629},
{"learn":[6.282040317],"iteration":51,"passed_time":0.1764414784,"remaining_time":3.216663876},
{"learn":[6.237655841],"iteration":52,"passed_time":0.1774251952,"remaining_time":3.170219997},
{"learn":[6.192792003],"iteration":53,"passed_time":0.178388096,"remaining_time":3.125095164},
{"learn":[6.150579347],"iteration":54,"passed_time":0.1795591015,"remaining_time":3.085151835},
{"learn":[6.115693845],"iteration":55,"passed_time":0.1805592536,"remaining_time":3.043713133},
{"learn":[6.078780782],"iteration":56,"passed_time":0.1815625832,"remaining_time":3.003745894},
{"learn":[6.045146957],"iteration":57,"passed_time":0.1824998782,"remaining_time":2.964049746},
{"learn":[6.008080327],"iteration":58,"passed_time":0.1835724589,"remaining_time":2.927825149},
{"learn":[5.977575734],"iteration":59,"passed_time":0.1845687837,"remaining_time":2.891577611},
{"learn":[5.948036502],"iteration":60,"passed_time":0.1856982069,"remaining_time":2.858534693},
{"learn":[5.914888282],"iteration":61,"passed_time":0.1867827241,"remaining_time":2.825841859},
{"learn":[5.884957796],"iteration":62,"passed_time":0.187892267,"remaining_time":2.79452467},
{"learn":[5.849539885],"iteration":63,"passed_time":0.1889668721,"remaining_time":2.763640505},
{"learn":[5.821387627],"iteration":64,"passed_time":0.1899365583,"remaining_time":2.732164338},
{"learn":[5.797012279],"iteration":65,"passed_time":0.1913152415,"remaining_time":2.707400538},
{"learn":[5.768685095],"iteration":66,"passed_time":0.1923979543,"remaining_time":2.679213304},
{"learn":[5.755484587],"iteration":67,"passed_time":0.1930294724,"remaining_time":2.64563924},
{"learn":[5.731887055],"iteration":68,"passed_time":0.1952163549,"remaining_time":2.63400618},
{"learn":[5.707148487],"iteration":69,"passed_time":0.196560859,"remaining_time":2.611451413},
{"learn":[5.685365039],"iteration":70,"passed_time":0.1976644875,"remaining_time":2.586342378},
{"learn":[5.663541834],"iteration":71,"passed_time":0.1991473335,"remaining_time":2.566787854},
{"learn":[5.638108797],"iteration":72,"passed_time":0.2007405905,"remaining_time":2.549130512},
{"learn":[5.619204893],"iteration":73,"passed_time":0.2020564821,"remaining_time":2.52843652},
{"learn":[5.598472793],"iteration":74,"passed_time":0.2056222237,"remaining_time":2.536007425},
{"learn":[5.577007075],"iteration":75,"passed_time":0.2070048409,"remaining_time":2.516743066},
{"learn":[5.562637084],"iteration":76,"passed_time":0.2083968688,"remaining_time":2.498055972},
{"learn":[5.54729991],"iteration":77,"passed_time":0.2095965068,"remaining_time":2.477538195},
{"learn":[5.530737623],"iteration":78,"passed_time":0.2109314094,"remaining_time":2.459086431},
{"learn":[5.513704873],"iteration":79,"passed_time":0.2123771946,"remaining_time":2.442337737},
{"learn":[5.501575529],"iteration":80,"passed_time":0.2137347271,"remaining_time":2.424965608},
{"learn":[5.484080734],"iteration":81,"passed_time":0.2154623774,"remaining_time":2.41212759},
{"learn":[5.472178894],"iteration":82,"passed_time":0.2168942221,"remaining_time":2.396289176},
{"learn":[5.458923342],"iteration":83,"passed_time":0.2182681604,"remaining_time":2.380162321},
{"learn":[5.451382371],"iteration":84,"passed_time":0.2190852636,"remaining_time":2.358388426},
{"learn":[5.441410748],"iteration":85,"passed_time":0.2204938977,"remaining_time":2.343388633},
{"learn":[5.434047468],"iteration":86,"passed_time":0.221762446,"remaining_time":2.327231186},
{"learn":[5.422107497],"iteration":87,"passed_time":0.2233341064,"remaining_time":2.314553466},
{"learn":[5.40731265],"iteration":88,"passed_time":0.2245703638,"remaining_time":2.29869215},
{"learn":[5.396360181],"iteration":89,"passed_time":0.2257871091,"remaining_time":2.282958547},
{"learn":[5.383793239],"iteration":90,"passed_time":0.2269646293,"remaining_time":2.267152176},
{"learn":[5.369605034],"iteration":91,"passed_time":0.22810573,"remaining_time":2.251304379},
{"learn":[5.357467333],"iteration":92,"passed_time":0.2291164557,"remaining_time":2.234501348},
{"learn":[5.341109968],"iteration":93,"passed_time":0.2301374438,"remaining_time":2.218133235},
{"learn":[5.330529276],"iteration":94,"passed_time":0.2313845654,"remaining_time":2.204242439},
{"learn":[5.319862075],"iteration":95,"passed_time":0.2326090777,"remaining_time":2.190402148},
{"learn":[5.313052243],"iteration":96,"passed_time":0.2340185436,"remaining_time":2.178543761},
{"learn":[5.299677207],"iteration":97,"passed_time":0.2352943477,"remaining_time":2.165668384},
{"learn":[5.287546698],"iteration":98,"passed_time":0.2367863036,"remaining_time":2.154994541},
{"learn":[5.279803754],"iteration":99,"passed_time":0.2380279232,"remaining_time":2.142251309},
{"learn":[5.272254612],"iteration":100,"passed_time":0.2392928737,"remaining_time":2.1299435},
{"learn":[5.268813888],"iteration":101,"passed_time":0.2399098301,"remaining_time":2.112147328},
{"learn":[5.258113767],"iteration":102,"passed_time":0.2410061927,"remaining_time":2.098859756},
{"learn":[5.251018576],"iteration":103,"passed_time":0.2419953915,"remaining_time":2.084883373},
{"learn":[5.24171237],"iteration":104,"passed_time":0.2429867048,"remaining_time":2.071172389},
{"learn":[5.233984943],"iteration":105,"passed_time":0.2439924296,"remaining_time":2.057822944},
{"learn":[5.226240449],"iteration":106,"passed_time":0.2456922591,"remaining_time":2.050497079},
{"learn":[5.220541644],"iteration":107,"passed_time":0.2467386928,"remaining_time":2.037878833},
{"learn":[5.211712096],"iteration":108,"passed_time":0.247974179,"remaining_time":2.027018289},
{"learn":[5.203388597],"iteration":109,"passed_time":0.2491212427,"remaining_time":2.015617328},
{"learn":[5.196026544],"iteration":110,"passed_time":0.2501694903,"remaining_time":2.003609702},
{"learn":[5.188716772],"iteration":111,"passed_time":0.2516190838,"remaining_time":1.994979879},
{"learn":[5.182163132],"iteration":112,"passed_time":0.2530299427,"remaining_time":1.98617309},
{"learn":[5.17764747],"iteration":113,"passed_time":0.2543352408,"remaining_time":1.976675643},
{"learn":[5.170548056],"iteration":114,"passed_time":0.2555575181,"remaining_time":1.96668177},
{"learn":[5.165901827],"iteration":115,"passed_time":0.2565891289,"remaining_time":1.95538612},
{"learn":[5.160333668],"iteration":116,"passed_time":0.2577955517,"remaining_time":1.945585232},
{"learn":[5.148953243],"iteration":117,"passed_time":0.2590145319,"remaining_time":1.936023874},
{"learn":[5.144729126],"iteration":118,"passed_time":0.2601133604,"remaining_time":1.925713197},
{"learn":[5.139939946],"iteration":119,"passed_time":0.261342852,"remaining_time":1.916514248},
{"learn":[5.132898872],"iteration":120,"passed_time":0.2623908891,"remaining_time":1.906128856},
{"learn":[5.129073077],"iteration":121,"passed_time":0.263760268,"remaining_time":1.898209142},
{"learn":[5.127123916],"iteration":122,"passed_time":0.2646326218,"remaining_time":1.886852108},
{"learn":[5.121282057],"iteration":123,"passed_time":0.2657135707,"remaining_time":1.877137806},
{"learn":[5.114489821],"iteration":124,"passed_time":0.2668683809,"remaining_time":1.868078666},
{"learn":[5.107777291],"iteration":125,"passed_time":0.268047003,"remaining_time":1.859310164},
{"learn":[5.103518754],"iteration":126,"passed_time":0.2692850548,"remaining_time":1.851069707},
{"learn":[5.101133351],"iteration":127,"passed_time":0.2701417078,"remaining_time":1.840340384},
{"learn":[5.096462705],"iteration":128,"passed_time":0.2713485314,"remaining_time":1.832128456},
{"learn":[5.08562082],"iteration":129,"passed_time":0.2724945218,"remaining_time":1.823617185},
{"learn":[5.080483682],"iteration":130,"passed_time":0.2736170916,"remaining_time":1.815062997},
{"learn":[5.07437499],"iteration":131,"passed_time":0.2746949037,"remaining_time":1.806327094},
{"learn":[5.070683732],"iteration":132,"passed_time":0.2762761094,"remaining_time":1.800987871},
{"learn":[5.06432037],"iteration":133,"passed_time":0.2773380168,"remaining_time":1.792348676},
{"learn":[5.057436484],"iteration":134,"passed_time":0.2783744882,"remaining_time":1.783658758},
{"learn":[5.053254656],"iteration":135,"passed_time":0.2794080533,"remaining_time":1.775062927},
{"learn":[5.04801663],"iteration":136,"passed_time":0.2804303938,"remaining_time":1.766506787},
{"learn":[5.045680836],"iteration":137,"passed_time":0.2812910425,"remaining_time":1.757049845},
{"learn":[5.041857933],"iteration":138,"passed_time":0.2822886897,"remaining_time":1.748565193},
{"learn":[5.035264888],"iteration":139,"passed_time":0.2832182883,"remaining_time":1.739769486},
{"learn":[5.028771948],"iteration":140,"passed_time":0.2842470229,"remaining_time":1.731689309},
{"learn":[5.024912247],"iteration":141,"passed_time":0.2852806085,"remaining_time":1.723737761},
{"learn":[5.02239068],"iteration":142,"passed_time":0.286322172,"remaining_time":1.715930779},
{"learn":[5.017110572],"iteration":143,"passed_time":0.2873558979,"remaining_time":1.708171171},
{"learn":[5.010707886],"iteration":144,"passed_time":0.2888447069,"remaining_time":1.703187754},
{"learn":[5.004389868],"iteration":145,"passed_time":0.2899645813,"remaining_time":1.696094195},
{"learn":[4.997628683],"iteration":146,"passed_time":0.2909692939,"remaining_time":1.688413658},
{"learn":[4.991497851],"iteration":147,"passed_time":0.2920752474,"remaining_time":1.681406154},
{"learn":[4.988345253],"iteration":148,"passed_time":0.2931684737,"remaining_time":1.674405175},
{"learn":[4.98460423],"iteration":149,"passed_time":0.2944112358,"remaining_time":1.668330336},
{"learn":[4.982441783],"iteration":150,"passed_time":0.2954569628,"remaining_time":1.661211665},
{"learn":[4.977461771],"iteration":151,"passed_time":0.2965380426,"remaining_time":1.654370132},
{"learn":[4.973601586],"iteration":152,"passed_time":0.2977209641,"remaining_time":1.64816769},
{"learn":[4.968328804],"iteration":153,"passed_time":0.2988095928,"remaining_time":1.641512438},
{"learn":[4.9640736],"iteration":154,"passed_time":0.2999990566,"remaining_time":1.635478728},
{"learn":[4.960865882],"iteration":155,"passed_time":0.3012562917,"remaining_time":1.629873784},
{"learn":[4.957014156],"iteration":156,"passed_time":0.3025522199,"remaining_time":1.624531983},
{"learn":[4.952244852],"iteration":157,"passed_time":0.3035570226,"remaining_time":1.617689956},
{"learn":[4.949695675],"iteration":158,"passed_time":0.3044223611,"remaining_time":1.610183683},
{"learn":[4.946584698],"iteration":159,"passed_time":0.3054572194,"remaining_time":1.603650402},
{"learn":[4.940192834],"iteration":160,"passed_time":0.3063696106,"remaining_time":1.596547225},
{"learn":[4.936727994],"iteration":161,"passed_time":0.3072640725,"remaining_time":1.589427733},
{"learn":[4.932342063],"iteration":162,"passed_time":0.3082427583,"remaining_time":1.582817109},
{"learn":[4.925830838],"iteration":163,"passed_time":0.3093529712,"remaining_time":1.576945633},
{"learn":[4.922571773],"iteration":164,"passed_time":0.3103654006,"remaining_time":1.570637027},
{"learn":[4.918395814],"iteration":165,"passed_time":0.3113158653,"remaining_time":1.564080914},
{"learn":[4.911142452],"iteration":166,"passed_time":0.3124151543,"remaining_time":1.558334273},
{"learn":[4.908276131],"iteration":167,"passed_time":0.3135557133,"remaining_time":1.552847342},
{"learn":[4.904584645],"iteration":168,"passed_time":0.3146788143,"remaining_time":1.547326004},
{"learn":[4.89795517],"iteration":169,"passed_time":0.3156415853,"remaining_time":1.541073622},
{"learn":[4.895556491],"iteration":170,"passed_time":0.3166485824,"remaining_time":1.535097514},
{"learn":[4.890591233],"iteration":171,"passed_time":0.3176189099,"remaining_time":1.52900266},
{"learn":[4.884629277],"iteration":172,"passed_time":0.3184977679,"remaining_time":1.522529792},
{"learn":[4.880550786],"iteration":173,"passed_time":0.3194053981,"remaining_time":1.516257809},
{"learn":[4.876384842],"iteration":174,"passed_time":0.3202552222,"remaining_time":1.509774619},
{"learn":[4.872638238],"iteration":175,"passed_time":0.3211351625,"remaining_time":1.503496443},
{"learn":[4.869137118],"iteration":176,"passed_time":0.3223508856,"remaining_time":1.498840558},
{"learn":[4.863587157],"iteration":177,"passed_time":0.3233986721,"remaining_time":1.493447801},
{"learn":[4.858028614],"iteration":178,"passed_time":0.3244305134,"remaining_time":1.488030455},
{"learn":[4.853838176],"iteration":179,"passed_time":0.3255427311,"remaining_time":1.483027997},
{"learn":[4.853462329],"iteration":180,"passed_time":0.3262035132,"remaining_time":1.476025841},
{"learn":[4.851573196],"iteration":181,"passed_time":0.3274945792,"remaining_time":1.471926185},
{"learn":[4.848442087],"iteration":182,"passed_time":0.3285149755,"remaining_time":1.466648825},
{"learn":[4.845547104],"iteration":183,"passed_time":0.3294914164,"remaining_time":1.461222803},
{"learn":[4.839868817],"iteration":184,"passed_time":0.3304896643,"remaining_time":1.455940954},
{"learn":[4.836336958],"iteration":185,"passed_time":0.3314613353,"remaining_time":1.450588855},
{"learn":[4.831124789],"iteration":186,"passed_time":0.3324282855,"remaining_time":1.445263081},
{"learn":[4.827407333],"iteration":187,"passed_time":0.333454284,"remaining_time":1.440238716},
{"learn":[4.824088918],"iteration":188,"passed_time":0.334404417,"remaining_time":1.434931123},
{"learn":[4.820934539],"iteration":189,"passed_time":0.3354026856,"remaining_time":1.429874607},
{"learn":[4.816975227],"iteration":190,"passed_time":0.3363730833,"remaining_time":1.424742536},
{"learn":[4.812340486],"iteration":191,"passed_time":0.3374350408,"remaining_time":1.42003913},
{"learn":[4.806402747],"iteration":192,"passed_time":0.3385973172,"remaining_time":1.415792927},
{"learn":[4.801521788],"iteration":193,"passed_time":0.3396104782,"remaining_time":1.410958997},
{"learn":[4.797601172],"iteration":194,"passed_time":0.3405178684,"remaining_time":1.405727611},
{"learn":[4.792694629],"iteration":195,"passed_time":0.3413871555,"remaining_time":1.400384046},
{"learn":[4.789794613],"iteration":196,"passed_time":0.3424008973,"remaining_time":1.395674723},
{"learn":[4.785367055],"iteration":197,"passed_time":0.343393293,"remaining_time":1.390916268},
{"learn":[4.780376856],"iteration":198,"passed_time":0.3442761391,"remaining_time":1.385754711},
{"learn":[4.776691261],"iteration":199,"passed_time":0.3451745397,"remaining_time":1.380698159},
{"learn":[4.773470753],"iteration":200,"passed_time":0.3460972634,"remaining_time":1.375779669},
{"learn":[4.77207327],"iteration":201,"passed_time":0.3471244044,"remaining_time":1.371313241},
{"learn":[4.767347177],"iteration":202,"passed_time":0.3480770935,"remaining_time":1.366588392},
{"learn":[4.763983068],"iteration":203,"passed_time":0.3489264976,"remaining_time":1.36149751},
{"learn":[4.761588849],"iteration":204,"passed_time":0.3497749888,"remaining_time":1.356444469},
{"learn":[4.758558086],"iteration":205,"passed_time":0.3510488788,"remaining_time":1.353071892},
{"learn":[4.753678804],"iteration":206,"passed_time":0.3521465638,"remaining_time":1.349044566},
{"learn":[4.746510889],"iteration":207,"passed_time":0.3531483299,"remaining_time":1.344680179},
{"learn":[4.744840601],"iteration":208,"passed_time":0.3540614627,"remaining_time":1.340012521},
{"learn":[4.741702222],"iteration":209,"passed_time":0.3549633008,"remaining_time":1.335338131},
{"learn":[4.739352853],"iteration":210,"passed_time":0.3559019792,"remaining_time":1.330837259},
{"learn":[4.735539287],"iteration":211,"passed_time":0.3568303653,"remaining_time":1.326331735},
{"learn":[4.730726751],"iteration":212,"passed_time":0.3577814107,"remaining_time":1.321943522},
{"learn":[4.726416092],"iteration":213,"passed_time":0.3586164731,"remaining_time":1.317161439},
{"learn":[4.721293082],"iteration":214,"passed_time":0.3595903779,"remaining_time":1.312923008},
{"learn":[4.718443695],"iteration":215,"passed_time":0.3606562841,"remaining_time":1.309048735},
{"learn":[4.711627962],"iteration":216,"passed_time":0.3616630717,"remaining_time":1.304987028},
{"learn":[4.709790764],"iteration":217,"passed_time":0.3626565397,"remaining_time":1.300905569},
{"learn":[4.706913073],"iteration":218,"passed_time":0.3639270323,"remaining_time":1.297840239},
{"learn":[4.703846389],"iteration":219,"passed_time":0.3650712764,"remaining_time":1.294343616},
{"learn":[4.701001135],"iteration":220,"passed_time":0.3660034607,"remaining_time":1.290120796},
{"learn":[4.700380864],"iteration":221,"passed_time":0.3671752073,"remaining_time":1.286767168},
{"learn":[4.695837486],"iteration":222,"passed_time":0.3682310716,"remaining_time":1.283029339},
{"learn":[4.691242996],"iteration":223,"passed_time":0.3691894626,"remaining_time":1.278977781},
{"learn":[4.690284609],"iteration":224,"passed_time":0.370063721,"remaining_time":1.274663928},
{"learn":[4.68827119],"iteration":225,"passed_time":0.3709650078,"remaining_time":1.27047308},
{"learn":[4.686922425],"iteration":226,"passed_time":0.3720331684,"remaining_time":1.266879468},
{"learn":[4.686085874],"iteration":227,"passed_time":0.3730701614,"remaining_time":1.263202476},
{"learn":[4.683230741],"iteration":228,"passed_time":0.374256791,"remaining_time":1.26005234},
{"learn":[4.6773487],"iteration":229,"passed_time":0.3753258841,"remaining_time":1.256525786},
{"learn":[4.671462906],"iteration":230,"passed_time":0.3769583582,"remaining_time":1.254896006},
{"learn":[4.664799601],"iteration":231,"passed_time":0.3782775786,"remaining_time":1.252229226},
{"learn":[4.660979386],"iteration":232,"passed_time":0.3792797752,"remaining_time":1.248530419},
{"learn":[4.656281279],"iteration":233,"passed_time":0.3802729927,"remaining_time":1.244825267},
{"learn":[4.651997094],"iteration":234,"passed_time":0.3813280251,"remaining_time":1.241344422},
{"learn":[4.650151977],"iteration":235,"passed_time":0.3822275281,"remaining_time":1.237380642},
{"learn":[4.648478046],"iteration":236,"passed_time":0.3832004809,"remaining_time":1.233679185},
{"learn":[4.646364602],"iteration":237,"passed_time":0.3843979837,"remaining_time":1.230719595},
{"learn":[4.642635873],"iteration":238,"passed_time":0.3854414604,"remaining_time":1.227284315},
{"learn":[4.640860821],"iteration":239,"passed_time":0.3864981559,"remaining_time":1.223910827},
{"learn":[4.639446822],"iteration":240,"passed_time":0.3875159054,"remaining_time":1.22043391},
{"learn":[4.637120072],"iteration":241,"passed_time":0.3890651965,"remaining_time":1.218642227},
{"learn":[4.633769267],"iteration":242,"passed_time":0.3902151545,"remaining_time":1.215608527},
{"learn":[4.630491517],"iteration":243,"passed_time":0.3913545109,"remaining_time":1.212557419},
{"learn":[4.627813333],"iteration":244,"passed_time":0.3923529799,"remaining_time":1.209087754},
{"learn":[4.622496304],"iteration":245,"passed_time":0.3933492942,"remaining_time":1.205631576},
{"learn":[4.618979301],"iteration":246,"passed_time":0.3942680792,"remaining_time":1.201958962},
{"learn":[4.616563458],"iteration":247,"passed_time":0.3952657264,"remaining_time":1.198547686},
{"learn":[4.614759385],"iteration":248,"passed_time":0.396302289,"remaining_time":1.195273169},
{"learn":[4.61251363],"iteration":249,"passed_time":0.3973277569,"remaining_time":1.191983271},
{"learn":[4.608796693],"iteration":250,"passed_time":0.3984287496,"remaining_time":1.188936787},
{"learn":[4.60847774],"iteration":251,"passed_time":0.3993059935,"remaining_time":1.1852416},
{"learn":[4.605195659],"iteration":252,"passed_time":0.4001381896,"remaining_time":1.181435682},
{"learn":[4.60103766],"iteration":253,"passed_time":0.4012850108,"remaining_time":1.178577236},
{"learn":[4.599325598],"iteration":254,"passed_time":0.4028586745,"remaining_time":1.176979265},
{"learn":[4.597012808],"iteration":255,"passed_time":0.4038998868,"remaining_time":1.173834046},
{"learn":[4.594161533],"iteration":256,"passed_time":0.4049047998,"remaining_time":1.170600258},
{"learn":[4.592197259],"iteration":257,"passed_time":0.4059190126,"remaining_time":1.167410494},
{"learn":[4.58952828],"iteration":258,"passed_time":0.4068888391,"remaining_time":1.16411054},
{"learn":[4.585816572],"iteration":259,"passed_time":0.4078195907,"remaining_time":1.160717297},
{"learn":[4.582934052],"iteration":260,"passed_time":0.4087583594,"remaining_time":1.157365623},
{"learn":[4.582234842],"iteration":261,"passed_time":0.4097716903,"remaining_time":1.154242395},
{"learn":[4.57571562],"iteration":262,"passed_time":0.4108173117,"remaining_time":1.151225698},
{"learn":[4.571197349],"iteration":263,"passed_time":0.4117227471,"remaining_time":1.147833113},
{"learn":[4.56723703],"iteration":264,"passed_time":0.4126916295,"remaining_time":1.144635274},
{"learn":[4.560335567],"iteration":265,"passed_time":0.4140449699,"remaining_time":1.142515067},
{"learn":[4.554709345],"iteration":266,"passed_time":0.4151558642,"remaining_time":1.139735013},
{"learn":[4.552806306],"iteration":267,"passed_time":0.4160947126,"remaining_time":1.136497499},
{"learn":[4.550766241],"iteration":268,"passed_time":0.4170110523,"remaining_time":1.133215908},
{"learn":[4.549216045],"iteration":269,"passed_time":0.4178804396,"remaining_time":1.129824892},
{"learn":[4.547687452],"iteration":270,"passed_time":0.4188382799,"remaining_time":1.126690428},
{"learn":[4.545642435],"iteration":271,"passed_time":0.4196869013,"remaining_time":1.123279648},
{"learn":[4.543930359],"iteration":272,"passed_time":0.420613513,"remaining_time":1.120095326},
{"learn":[4.541029943],"iteration":273,"passed_time":0.4216707286,"remaining_time":1.117273536},
{"learn":[4.537781449],"iteration":274,"passed_time":0.422783267,"remaining_time":1.114610431},
{"learn":[4.53066128],"iteration":275,"passed_time":0.4237831591,"remaining_time":1.11166307},
{"learn":[4.526763956],"iteration":276,"passed_time":0.4248115839,"remaining_time":1.108804243},
{"learn":[4.522036004],"iteration":277,"passed_time":0.4261504558,"remaining_time":1.106764853},
{"learn":[4.515307629],"iteration":278,"passed_time":0.4272020406,"remaining_time":1.103988069},
{"learn":[4.51109143],"iteration":279,"passed_time":0.4281388651,"remaining_time":1.10092851},
{"learn":[4.508233494],"iteration":280,"passed_time":0.4290078114,"remaining_time":1.097710379},
{"learn":[4.502555629],"iteration":281,"passed_time":0.4300032232,"remaining_time":1.094830902},
{"learn":[4.500081355],"iteration":282,"passed_time":0.4310127768,"remaining_time":1.092000569},
{"learn":[4.495281743],"iteration":283,"passed_time":0.4319054945,"remaining_time":1.0888885},
{"learn":[4.492138869],"iteration":284,"passed_time":0.432829957,"remaining_time":1.085871646},
{"learn":[4.491708261],"iteration":285,"passed_time":0.433666462,"remaining_time":1.082649839},
{"learn":[4.489398865],"iteration":286,"passed_time":0.4345192926,"remaining_time":1.079485211},
{"learn":[4.485796373],"iteration":287,"passed_time":0.4356541888,"remaining_time":1.077033967},
{"learn":[4.479542205],"iteration":288,"passed_time":0.4366391783,"remaining_time":1.07422303},
{"learn":[4.475986993],"iteration":289,"passed_time":0.437564417,"remaining_time":1.0712784},
{"learn":[4.468661855],"iteration":290,"passed_time":0.4384960401,"remaining_time":1.068363204},
{"learn":[4.463785664],"iteration":291,"passed_time":0.4395639701,"remaining_time":1.065792092},
{"learn":[4.460445831],"iteration":292,"passed_time":0.4406338755,"remaining_time":1.063236007},
{"learn":[4.45692492],"iteration":293,"passed_time":0.4416692264,"remaining_time":1.060607054},
{"learn":[4.454031688],"iteration":294,"passed_time":0.4425702828,"remaining_time":1.057667964},
{"learn":[4.451672391],"iteration":295,"passed_time":0.4435505115,"remaining_time":1.054930946},
{"learn":[4.45031553],"iteration":296,"passed_time":0.4444285376,"remaining_time":1.051963845},
{"learn":[4.446782666],"iteration":297,"passed_time":0.4454221259,"remaining_time":1.049282995},
{"learn":[4.444369689],"iteration":298,"passed_time":0.4463250864,"remaining_time":1.046400955},
{"learn":[4.44411683],"iteration":299,"passed_time":0.4472287079,"remaining_time":1.043533652},
{"learn":[4.440876943],"iteration":300,"passed_time":0.4481169869,"remaining_time":1.040643767},
{"learn":[4.439336453],"iteration":301,"passed_time":0.4489836081,"remaining_time":1.037717081},
{"learn":[4.436666901],"iteration":302,"passed_time":0.4499389535,"remaining_time":1.035008088},
{"learn":[4.433043336],"iteration":303,"passed_time":0.4513224928,"remaining_time":1.03329097},
{"learn":[4.431419305],"iteration":304,"passed_time":0.4525339811,"remaining_time":1.03118399},
{"learn":[4.428859646],"iteration":305,"passed_time":0.4535421112,"remaining_time":1.028621651},
{"learn":[4.424552441],"iteration":306,"passed_time":0.4545066155,"remaining_time":1.025970959},
{"learn":[4.422706391],"iteration":307,"passed_time":0.4557172655,"remaining_time":1.023884246},
{"learn":[4.421427994],"iteration":308,"passed_time":0.4567408493,"remaining_time":1.021384877},
{"learn":[4.418733158],"iteration":309,"passed_time":0.4577364615,"remaining_time":1.018832769},
{"learn":[4.415656941],"iteration":310,"passed_time":0.4587641137,"remaining_time":1.016361654},
{"learn":[4.410747417],"iteration":311,"passed_time":0.4598541525,"remaining_time":1.014037362},
{"learn":[4.408126521],"iteration":312,"passed_time":0.46093447,"remaining_time":1.01169962},
{"learn":[4.407843853],"iteration":313,"passed_time":0.4618922703,"remaining_time":1.009102221},
{"learn":[4.405219398],"iteration":314,"passed_time":0.4628635198,"remaining_time":1.00654448},
{"learn":[4.402708465],"iteration":315,"passed_time":0.463797478,"remaining_time":1.00391606},
{"learn":[4.40104971],"iteration":316,"passed_time":0.464768457,"remaining_time":1.001378095},
{"learn":[4.400830038],"iteration":317,"passed_time":0.4655720406,"remaining_time":0.9984909802},
{"learn":[4.39784288],"iteration":318,"passed_time":0.4666410435,"remaining_time":0.9961835443},
{"learn":[4.393741845],"iteration":319,"passed_time":0.4676925182,"remaining_time":0.9938466011},
{"learn":[4.393425936],"iteration":320,"passed_time":0.4685200837,"remaining_time":0.9910440399},
{"learn":[4.390505974],"iteration":321,"passed_time":0.4695181016,"remaining_time":0.9886126488},
{"learn":[4.390305136],"iteration":322,"passed_time":0.4703531444,"remaining_time":0.9858485412},
{"learn":[4.38568203],"iteration":323,"passed_time":0.4712426256,"remaining_time":0.9832099225},
{"learn":[4.383057135],"iteration":324,"passed_time":0.4721689671,"remaining_time":0.980658624},
{"learn":[4.380662684],"iteration":325,"passed_time":0.4731962189,"remaining_time":0.978325925},
{"learn":[4.37805727],"iteration":326,"passed_time":0.4740932465,"remaining_time":0.9757331954},
{"learn":[4.373708319],"iteration":327,"passed_time":0.4749749506,"remaining_time":0.9731194111},
{"learn":[4.36887921],"iteration":328,"passed_time":0.4758575462,"remaining_time":0.9705179742},
{"learn":[4.367895929],"iteration":329,"passed_time":0.4767297,"remaining_time":0.9679057546},
{"learn":[4.362140573],"iteration":330,"passed_time":0.4776375813,"remaining_time":0.9653762595},
{"learn":[4.361931924],"iteration":331,"passed_time":0.478474157,"remaining_time":0.9627130628},
{"learn":[4.359656377],"iteration":332,"passed_time":0.4793383524,"remaining_time":0.9601161593},
{"learn":[4.354281355],"iteration":333,"passed_time":0.4801923361,"remaining_time":0.9575092689},
{"learn":[4.348589447],"iteration":334,"passed_time":0.4810311767,"remaining_time":0.9548827835},
{"learn":[4.346355698],"iteration":335,"passed_time":0.4819233131,"remaining_time":0.9523722615},
{"learn":[4.343894047],"iteration":336,"passed_time":0.4827906253,"remaining_time":0.9498225062},
{"learn":[4.341561356],"iteration":337,"passed_time":0.4837498887,"remaining_time":0.9474627998},
{"learn":[4.338869061],"iteration":338,"passed_time":0.4846431882,"remaining_time":0.9449827356},
{"learn":[4.333720063],"iteration":339,"passed_time":0.4856647671,"remaining_time":0.9427610184},
{"learn":[4.330892223],"iteration":340,"passed_time":0.4865501187,"remaining_time":0.9402830739},
{"learn":[4.328311474],"iteration":341,"passed_time":0.4873565886,"remaining_time":0.9376626764},
{"learn":[4.324580133],"iteration":342,"passed_time":0.4883029043,"remaining_time":0.9353207234},
{"learn":[4.323354432],"iteration":343,"passed_time":0.4892593315,"remaining_time":0.933006167},
{"learn":[4.323159553],"iteration":344,"passed_time":0.4902881567,"remaining_time":0.9308369352},
{"learn":[4.318639682],"iteration":345,"passed_time":0.4911450362,"remaining_time":0.928349288},
{"learn":[4.312712208],"iteration":346,"passed_time":0.492012409,"remaining_time":0.925890787},
{"learn":[4.311461062],"iteration":347,"passed_time":0.4929028422,"remaining_time":0.9234846355},
{"learn":[4.311178356],"iteration":348,"passed_time":0.493793997,"remaining_time":0.9210885159},
{"learn":[4.311102505],"iteration":349,"passed_time":0.494639652,"remaining_time":0.9186164965},
{"learn":[4.310232308],"iteration":350,"passed_time":0.495432853,"remaining_time":0.9160567567},
{"learn":[4.305128197],"iteration":351,"passed_time":0.4962375691,"remaining_time":0.9135282523},
{"learn":[4.304595496],"iteration":352,"passed_time":0.497238724,"remaining_time":0.9113695592},
{"learn":[4.3004992],"iteration":353,"passed_time":0.4981581404,"remaining_time":0.9090682449},
{"learn":[4.297581524],"iteration":354,"passed_time":0.499141316,"remaining_time":0.90689056},
{"learn":[4.297355825],"iteration":355,"passed_time":0.5000574553,"remaining_time":0.904598318},
{"learn":[4.295758715],"iteration":356,"passed_time":0.5009150764,"remaining_time":0.9022083868},
{"learn":[4.292500657],"iteration":357,"passed_time":0.5019559373,"remaining_time":0.9001556195},
{"learn":[4.290797586],"iteration":358,"passed_time":0.5030321455,"remaining_time":0.8981716023},
{"learn":[4.286410608],"iteration":359,"passed_time":0.5043192358,"remaining_time":0.8965675303},
{"learn":[4.280278245],"iteration":360,"passed_time":0.5055049133,"remaining_time":0.8947857052},
{"learn":[4.279941283],"iteration":361,"passed_time":0.5064421787,"remaining_time":0.8925693646},
{"learn":[4.274426275],"iteration":362,"passed_time":0.5074939234,"remaining_time":0.890560962},
{"learn":[4.273567658],"iteration":363,"passed_time":0.5090050166,"remaining_time":0.8893604136},
{"learn":[4.269488271],"iteration":364,"passed_time":0.5102849999,"remaining_time":0.8877560957},
{"learn":[4.266838205],"iteration":365,"passed_time":0.5114627917,"remaining_time":0.8859765299},
{"learn":[4.263456509],"iteration":366,"passed_time":0.5125144898,"remaining_time":0.8839827576},
{"learn":[4.260360204],"iteration":367,"passed_time":0.5138573574,"remaining_time":0.8824941572},
{"learn":[4.255120549],"iteration":368,"passed_time":0.5150731205,"remaining_time":0.8807889947},
{"learn":[4.252582211],"iteration":369,"passed_time":0.5161646726,"remaining_time":0.8788749831},
{"learn":[4.247857931],"iteration":370,"passed_time":0.5171666492,"remaining_time":0.8768135374},
{"learn":[4.245288911],"iteration":371,"passed_time":0.518258953,"remaining_time":0.8749102755},
{"learn":[4.24048515],"iteration":372,"passed_time":0.5194687511,"remaining_time":0.8732088658},
{"learn":[4.2378365],"iteration":373,"passed_time":0.5205859893,"remaining_time":0.8713551585},
{"learn":[4.236751063],"iteration":374,"passed_time":0.5220217325,"remaining_time":0.8700362208},
{"learn":[4.233240093],"iteration":375,"passed_time":0.5231338089,"remaining_time":0.8681795126},
{"learn":[4.230358421],"iteration":376,"passed_time":0.5243708485,"remaining_time":0.8665332589},
{"learn":[4.225853583],"iteration":377,"passed_time":0.5270914857,"remaining_time":0.8673304342},
{"learn":[4.224702126],"iteration":378,"passed_time":0.5283189144,"remaining_time":0.86566239},
{"learn":[4.224361982],"iteration":379,"passed_time":0.529415048,"remaining_time":0.8637824467},
{"learn":[4.223787954],"iteration":380,"passed_time":0.5303984455,"remaining_time":0.8617234588},
{"learn":[4.22144054],"iteration":381,"passed_time":0.5316286903,"remaining_time":0.8600694519},
{"learn":[4.217739335],"iteration":382,"passed_time":0.5328383632,"remaining_time":0.8583845172},
{"learn":[4.215611665],"iteration":383,"passed_time":0.5340636972,"remaining_time":0.856727181},
{"learn":[4.210236863],"iteration":384,"passed_time":0.5350387952,"remaining_time":0.8546723611},
{"learn":[4.208454294],"iteration":385,"passed_time":0.5360142038,"remaining_time":0.8526236299},
{"learn":[4.207446501],"iteration":386,"passed_time":0.5370449628,"remaining_time":0.8506681193},
{"learn":[4.204985442],"iteration":387,"passed_time":0.5385151411,"remaining_time":0.8494104803},
{"learn":[4.202796622],"iteration":388,"passed_time":0.539621956,"remaining_time":0.8475810158},
{"learn":[4.199774004],"iteration":389,"passed_time":0.5406473142,"remaining_time":0.8456278504},
{"learn":[4.199458358],"iteration":390,"passed_time":0.5416379756,"remaining_time":0.8436253891},
{"learn":[4.19751254],"iteration":391,"passed_time":0.5432152176,"remaining_time":0.8425378886},
{"learn":[4.195201346],"iteration":392,"passed_time":0.5443425383,"remaining_time":0.840752979},
{"learn":[4.190593508],"iteration":393,"passed_time":0.5453693792,"remaining_time":0.8388168624},
{"learn":[4.187212054],"iteration":394,"passed_time":0.5463531425,"remaining_time":0.8368193702},
{"learn":[4.184984466],"iteration":395,"passed_time":0.5474356454,"remaining_time":0.8349776005},
{"learn":[4.182832144],"iteration":396,"passed_time":0.5485080161,"remaining_time":0.8331242663},
{"learn":[4.179752812],"iteration":397,"passed_time":0.5499462348,"remaining_time":0.8318282244},
{"learn":[4.17878934],"iteration":398,"passed_time":0.5511593116,"remaining_time":0.8301923465},
{"learn":[4.174548229],"iteration":399,"passed_time":0.5523425638,"remaining_time":0.8285138457},
{"learn":[4.168872556],"iteration":400,"passed_time":0.5534779721,"remaining_time":0.8267663473},
{"learn":[4.163926494],"iteration":401,"passed_time":0.5546263682,"remaining_time":0.8250412144},
{"learn":[4.159485076],"iteration":402,"passed_time":0.5557682602,"remaining_time":0.8233093085},
{"learn":[4.155926102],"iteration":403,"passed_time":0.5567726927,"remaining_time":0.8213775367},
{"learn":[4.153540115],"iteration":404,"passed_time":0.5578562869,"remaining_time":0.8195666437},
{"learn":[4.150983044],"iteration":405,"passed_time":0.5590109262,"remaining_time":0.8178632762},
{"learn":[4.146539132],"iteration":406,"passed_time":0.5601088306,"remaining_time":0.8160799424},
{"learn":[4.144869174],"iteration":407,"passed_time":0.561172575,"remaining_time":0.814250403},
{"learn":[4.142825962],"iteration":408,"passed_time":0.5628612287,"remaining_time":0.8133275945},
{"learn":[4.142467378],"iteration":409,"passed_time":0.5642275504,"remaining_time":0.8119372067},
{"learn":[4.141800768],"iteration":410,"passed_time":0.5653812767,"remaining_time":0.8102422676},
{"learn":[4.140107084],"iteration":411,"passed_time":0.5665599374,"remaining_time":0.8085855417},
{"learn":[4.136243196],"iteration":412,"passed_time":0.5685022967,"remaining_time":0.8080165815},
{"learn":[4.133618439],"iteration":413,"passed_time":0.5698793704,"remaining_time":0.806640848},
{"learn":[4.131053025],"iteration":414,"passed_time":0.5711504137,"remaining_time":0.8051156434},
{"learn":[4.128379975],"iteration":415,"passed_time":0.5723478674,"remaining_time":0.8034883523},
{"learn":[4.127068571],"iteration":416,"passed_time":0.573483875,"remaining_time":0.8017772162},
{"learn":[4.125969877],"iteration":417,"passed_time":0.5744418341,"remaining_time":0.7998209269},
{"learn":[4.123893633],"iteration":418,"passed_time":0.5758555487,"remaining_time":0.7985013695},
{"learn":[4.119643722],"iteration":419,"passed_time":0.5769915579,"remaining_time":0.7967978656},
{"learn":[4.11465686],"iteration":420,"passed_time":0.5780249936,"remaining_time":0.7949559889},
{"learn":[4.111565986],"iteration":421,"passed_time":0.5793770342,"remaining_time":0.7935543265},
{"learn":[4.106322452],"iteration":422,"passed_time":0.5805305119,"remaining_time":0.7918820458},
{"learn":[4.104222175],"iteration":423,"passed_time":0.581589272,"remaining_time":0.7900835393},
{"learn":[4.103008002],"iteration":424,"passed_time":0.5827534526,"remaining_time":0.7884311417},
{"learn":[4.099176337],"iteration":425,"passed_time":0.5838778659,"remaining_time":0.7867274531},
{"learn":[4.096525716],"iteration":426,"passed_time":0.5849752793,"remaining_time":0.7849902459},
{"learn":[4.094967724],"iteration":427,"passed_time":0.5859433835,"remaining_time":0.7830832134},
{"learn":[4.094683584],"iteration":428,"passed_time":0.5870883937,"remaining_time":0.7814160206},
{"learn":[4.091096563],"iteration":429,"passed_time":0.5885190909,"remaining_time":0.7801299578},
{"learn":[4.089178677],"iteration":430,"passed_time":0.5896554308,"remaining_time":0.7784546174},
{"learn":[4.085335077],"iteration":431,"passed_time":0.5906500614,"remaining_time":0.7765954511},
{"learn":[4.084852122],"iteration":432,"passed_time":0.5917827132,"remaining_time":0.7749210124},
{"learn":[4.080322952],"iteration":433,"passed_time":0.5928490803,"remaining_time":0.7731626255},
{"learn":[4.077449519],"iteration":434,"passed_time":0.5938447732,"remaining_time":0.771315625},
{"learn":[4.076568374],"iteration":435,"passed_time":0.5947783806,"remaining_time":0.7693922171},
{"learn":[4.076071793],"iteration":436,"passed_time":0.5957544407,"remaining_time":0.7675280323},
{"learn":[4.075027644],"iteration":437,"passed_time":0.5967133834,"remaining_time":0.7656459394},
{"learn":[4.07020837],"iteration":438,"passed_time":0.5977351647,"remaining_time":0.763848354},
{"learn":[4.06833694],"iteration":439,"passed_time":0.5986674808,"remaining_time":0.7619404301},
{"learn":[4.063936568],"iteration":440,"passed_time":0.5996943417,"remaining_time":0.7601567733},
{"learn":[4.061734926],"iteration":441,"passed_time":0.6012478269,"remaining_time":0.7590413742},
{"learn":[4.060815619],"iteration":442,"passed_time":0.6023018676,"remaining_time":0.7572960277},
{"learn":[4.056407489],"iteration":443,"passed_time":0.6033079031,"remaining_time":0.7554936805},
{"learn":[4.05238936],"iteration":444,"passed_time":0.604349156,"remaining_time":0.753738835},
{"learn":[4.049685254],"iteration":445,"passed_time":0.6054547793,"remaining_time":0.7520671473},
{"learn":[4.045162016],"iteration":446,"passed_time":0.6065449383,"remaining_time":0.750378861},
{"learn":[4.042955482],"iteration":447,"passed_time":0.6075074789,"remaining_time":0.7485360008},
{"learn":[4.041467663],"iteration":448,"passed_time":0.6084951543,"remaining_time":0.7467279065},
{"learn":[4.038920476],"iteration":449,"passed_time":0.6094137394,"remaining_time":0.7448390148},
{"learn":[4.036694383],"iteration":450,"passed_time":0.610374917,"remaining_time":0.7430062737},
{"learn":[4.034999007],"iteration":451,"passed_time":0.6113510176,"remaining_time":0.7411954816},
{"learn":[4.031928018],"iteration":452,"passed_time":0.6122714764,"remaining_time":0.7393211867},
{"learn":[4.028718143],"iteration":453,"passed_time":0.6137044636,"remaining_time":0.7380674826},
{"learn":[4.027401978],"iteration":454,"passed_time":0.6150447269,"remaining_time":0.7367019257},
{"learn":[4.025930598],"iteration":455,"passed_time":0.6160572771,"remaining_time":0.7349455236},
{"learn":[4.021074523],"iteration":456,"passed_time":0.617109544,"remaining_time":0.7332395676},
{"learn":[4.020268486],"iteration":457,"passed_time":0.6184962101,"remaining_time":0.7319321963},
{"learn":[4.017986361],"iteration":458,"passed_time":0.6201123069,"remaining_time":0.7308948977},
{"learn":[4.014814804],"iteration":459,"passed_time":0.6212488567,"remaining_time":0.7292921362},
{"learn":[4.009704796],"iteration":460,"passed_time":0.6224297267,"remaining_time":0.7277432163},
{"learn":[4.008440457],"iteration":461,"passed_time":0.6234375556,"remaining_time":0.725994383},
{"learn":[4.004854849],"iteration":462,"passed_time":0.6246993939,"remaining_time":0.7245433574},
{"learn":[4.000898028],"iteration":463,"passed_time":0.6259044632,"remaining_time":0.7230275695},
{"learn":[3.996617985],"iteration":464,"passed_time":0.627060516,"remaining_time":0.7214567228},
{"learn":[3.995443319],"iteration":465,"passed_time":0.6280835892,"remaining_time":0.7197352717},
{"learn":[3.990771995],"iteration":466,"passed_time":0.6291166937,"remaining_time":0.7180282607},
{"learn":[3.989249359],"iteration":467,"passed_time":0.6303296307,"remaining_time":0.7165285546},
{"learn":[3.986599538],"iteration":468,"passed_time":0.6316142487,"remaining_time":0.7151112282},
{"learn":[3.985628919],"iteration":469,"passed_time":0.6330222318,"remaining_time":0.7138335806},
{"learn":[3.985086112],"iteration":470,"passed_time":0.6341123112,"remaining_time":0.7121983283},
{"learn":[3.98466839],"iteration":471,"passed_time":0.6352648664,"remaining_time":0.7106352743},
{"learn":[3.984233894],"iteration":472,"passed_time":0.636232247,"remaining_time":0.708867641},
{"learn":[3.981855845],"iteration":473,"passed_time":0.637364959,"remaining_time":0.7072868532},
{"learn":[3.978684264],"iteration":474,"passed_time":0.6385937606,"remaining_time":0.7058141564},
{"learn":[3.974361269],"iteration":475,"passed_time":0.6396335728,"remaining_time":0.7041344372},
{"learn":[3.972074049],"iteration":476,"passed_time":0.6407146219,"remaining_time":0.7025026148},
{"learn":[3.97191982],"iteration":477,"passed_time":0.6417674495,"remaining_time":0.7008422775},
{"learn":[3.969616848],"iteration":478,"passed_time":0.6436402065,"remaining_time":0.7000762997},
{"learn":[3.968533527],"iteration":479,"passed_time":0.6449974033,"remaining_time":0.6987471869},
{"learn":[3.967568753],"iteration":480,"passed_time":0.6460892465,"remaining_time":0.6971316402},
{"learn":[3.966232553],"iteration":481,"passed_time":0.6473108875,"remaining_time":0.6956577588},
{"learn":[3.961522393],"iteration":482,"passed_time":0.6487405079,"remaining_time":0.6944075415},
{"learn":[3.955829553],"iteration":483,"passed_time":0.6498904278,"remaining_time":0.69285839},
{"learn":[3.954248095],"iteration":484,"passed_time":0.6510168059,"remaining_time":0.6912858867},
{"learn":[3.951922606],"iteration":485,"passed_time":0.6521416908,"remaining_time":0.68971364},
{"learn":[3.94978202],"iteration":486,"passed_time":0.6531796464,"remaining_time":0.6880516604},
{"learn":[3.949518999],"iteration":487,"passed_time":0.6541441412,"remaining_time":0.6863151646},
{"learn":[3.945431216],"iteration":488,"passed_time":0.6551578931,"remaining_time":0.6846332993},
{"learn":[3.943249086],"iteration":489,"passed_time":0.6564840226,"remaining_time":0.6832792888},
{"learn":[3.941981548],"iteration":490,"passed_time":0.6578147471,"remaining_time":0.6819301554},
{"learn":[3.936600517],"iteration":491,"passed_time":0.6587537764,"remaining_time":0.6801766634},
{"learn":[3.934476885],"iteration":492,"passed_time":0.6597520549,"remaining_time":0.6784874074},
{"learn":[3.93045798],"iteration":493,"passed_time":0.6607031004,"remaining_time":0.6767525684},
{"learn":[3.925977375],"iteration":494,"passed_time":0.6616936115,"remaining_time":0.6750611592},
{"learn":[3.92457993],"iteration":495,"passed_time":0.6627583851,"remaining_time":0.6734480365},
{"learn":[3.919849146],"iteration":496,"passed_time":0.6637615944,"remaining_time":0.6717748129},
{"learn":[3.919681964],"iteration":497,"passed_time":0.664644401,"remaining_time":0.6699829102},
{"learn":[3.917633027],"iteration":498,"passed_time":0.6655472513,"remaining_time":0.6682147753},
{"learn":[3.916616419],"iteration":499,"passed_time":0.6664438179,"remaining_time":0.6664438179},
{"learn":[3.912896166],"iteration":500,"passed_time":0.6676296156,"remaining_time":0.6649644276},
{"learn":[3.912769674],"iteration":501,"passed_time":0.6687836541,"remaining_time":0.6634547007},
{"learn":[3.909373788],"iteration":502,"passed_time":0.6700329504,"remaining_time":0.6620405097},
{"learn":[3.906706036],"iteration":503,"passed_time":0.6711318586,"remaining_time":0.660478972},
{"learn":[3.903895664],"iteration":504,"passed_time":0.6721444779,"remaining_time":0.6588346863},
{"learn":[3.902982967],"iteration":505,"passed_time":0.6731646743,"remaining_time":0.6572002947},
{"learn":[3.900905528],"iteration":506,"passed_time":0.6741214924,"remaining_time":0.6555066977},
{"learn":[3.897463465],"iteration":507,"passed_time":0.6751083761,"remaining_time":0.6538451201},
{"learn":[3.895918033],"iteration":508,"passed_time":0.6760742339,"remaining_time":0.6521659112},
{"learn":[3.893921936],"iteration":509,"passed_time":0.6770034923,"remaining_time":0.6504543357},
{"learn":[3.890237934],"iteration":510,"passed_time":0.6779661426,"remaining_time":0.6487777764},
{"learn":[3.887311613],"iteration":511,"passed_time":0.6789286135,"remaining_time":0.6471038347},
{"learn":[3.884869735],"iteration":512,"passed_time":0.6800503194,"remaining_time":0.6455838315},
{"learn":[3.882101231],"iteration":513,"passed_time":0.6811994376,"remaining_time":0.644091297},
{"learn":[3.88060368],"iteration":514,"passed_time":0.682383461,"remaining_time":0.6426329681},
{"learn":[3.877726076],"iteration":515,"passed_time":0.6833889753,"remaining_time":0.6410082637},
{"learn":[3.874938145],"iteration":516,"passed_time":0.684358912,"remaining_time":0.6393527167},
{"learn":[3.874340833],"iteration":517,"passed_time":0.6852574825,"remaining_time":0.6376334104},
{"learn":[3.873105224],"iteration":518,"passed_time":0.6862383731,"remaining_time":0.6359935597},
{"learn":[3.869800236],"iteration":519,"passed_time":0.6872287945,"remaining_time":0.6343650411},
{"learn":[3.867932518],"iteration":520,"passed_time":0.6881569701,"remaining_time":0.6326817441},
{"learn":[3.866666962],"iteration":521,"passed_time":0.6890682588,"remaining_time":0.6309858768},
{"learn":[3.865527652],"iteration":522,"passed_time":0.6899707683,"remaining_time":0.6292850028},
{"learn":[3.861900081],"iteration":523,"passed_time":0.6911197858,"remaining_time":0.6278111032},
{"learn":[3.858502887],"iteration":524,"passed_time":0.6921072007,"remaining_time":0.6261922292},
{"learn":[3.858335097],"iteration":525,"passed_time":0.692918431,"remaining_time":0.6244169892},
{"learn":[3.855719306],"iteration":526,"passed_time":0.6939673801,"remaining_time":0.6228587681},
{"learn":[3.855137428],"iteration":527,"passed_time":0.6951673994,"remaining_time":0.6214375237},
{"learn":[3.851985706],"iteration":528,"passed_time":0.6962650148,"remaining_time":0.6199259394},
{"learn":[3.851051809],"iteration":529,"passed_time":0.6972423581,"remaining_time":0.618309261},
{"learn":[3.850679146],"iteration":530,"passed_time":0.6981629572,"remaining_time":0.6166448718},
{"learn":[3.848179484],"iteration":531,"passed_time":0.6990945206,"remaining_time":0.6149929242},
{"learn":[3.844551071],"iteration":532,"passed_time":0.700034983,"remaining_time":0.6133514767},
{"learn":[3.841604794],"iteration":533,"passed_time":0.701166152,"remaining_time":0.6118790765},
{"learn":[3.83969656],"iteration":534,"passed_time":0.7020402897,"remaining_time":0.6101845508},
{"learn":[3.836811463],"iteration":535,"passed_time":0.7029282675,"remaining_time":0.6085050674},
{"learn":[3.834182551],"iteration":536,"passed_time":0.7037715278,"remaining_time":0.6067899765},
{"learn":[3.828012842],"iteration":537,"passed_time":0.7046555174,"remaining_time":0.6051131023},
{"learn":[3.826636176],"iteration":538,"passed_time":0.7058147071,"remaining_time":0.6036745454},
{"learn":[3.826189798],"iteration":539,"passed_time":0.7069392046,"remaining_time":0.6022074706},
{"learn":[3.824104738],"iteration":540,"passed_time":0.7078823929,"remaining_time":0.6005878343},
{"learn":[3.82300218],"iteration":541,"passed_time":0.7087267551,"remaining_time":0.5988871842},
{"learn":[3.817146402],"iteration":542,"passed_time":0.7096344159,"remaining_time":0.5972429614},
{"learn":[3.814638044],"iteration":543,"passed_time":0.7105479194,"remaining_time":0.5956063442},
{"learn":[3.812979573],"iteration":544,"passed_time":0.7115036155,"remaining_time":0.5940076056},
{"learn":[3.811938825],"iteration":545,"passed_time":0.7123732634,"remaining_time":0.5923396732},
{"learn":[3.811479418],"iteration":546,"passed_time":0.7132024629,"remaining_time":0.5906411622},
{"learn":[3.80742981],"iteration":547,"passed_time":0.714046084,"remaining_time":0.5889577189},
{"learn":[3.805097043],"iteration":548,"passed_time":0.7149215345,"remaining_time":0.5873034828},
{"learn":[3.801577232],"iteration":549,"passed_time":0.7158467942,"remaining_time":0.5856928316},
{"learn":[3.799762083],"iteration":550,"passed_time":0.7166548571,"remaining_time":0.5839891667},
{"learn":[3.796393455],"iteration":551,"passed_time":0.7175021456,"remaining_time":0.582320582},
{"learn":[3.793486459],"iteration":552,"passed_time":0.7184096561,"remaining_time":0.5807036461},
{"learn":[3.792006091],"iteration":553,"passed_time":0.7194121734,"remaining_time":0.5791657569},
{"learn":[3.78932128],"iteration":554,"passed_time":0.7206280173,"remaining_time":0.5778008427},
{"learn":[3.787581812],"iteration":555,"passed_time":0.7216205934,"remaining_time":0.5762581717},
{"learn":[3.785308865],"iteration":556,"passed_time":0.7225674898,"remaining_time":0.5746811454},
{"learn":[3.78465475],"iteration":557,"passed_time":0.7234493543,"remaining_time":0.5730548648},
{"learn":[3.780498869],"iteration":558,"passed_time":0.7244222569,"remaining_time":0.5715030685},
{"learn":[3.778734909],"iteration":559,"passed_time":0.7253160074,"remaining_time":0.5698911486},
{"learn":[3.778652349],"iteration":560,"passed_time":0.7260920309,"remaining_time":0.5681896641},
{"learn":[3.777928006],"iteration":561,"passed_time":0.7269285564,"remaining_time":0.5665386258},
{"learn":[3.776131406],"iteration":562,"passed_time":0.7277477246,"remaining_time":0.5648770083},
{"learn":[3.772925617],"iteration":563,"passed_time":0.7286449727,"remaining_time":0.5632787377},
{"learn":[3.7727745],"iteration":564,"passed_time":0.7294554013,"remaining_time":0.5616161054},
{"learn":[3.771763073],"iteration":565,"passed_time":0.7303131331,"remaining_time":0.5599927558},
{"learn":[3.768738162],"iteration":566,"passed_time":0.7312415191,"remaining_time":0.5584260631},
{"learn":[3.767220794],"iteration":567,"passed_time":0.7322428844,"remaining_time":0.5569171234},
{"learn":[3.766691102],"iteration":568,"passed_time":0.7335405363,"remaining_time":0.5556343957},
{"learn":[3.766259335],"iteration":569,"passed_time":0.7344891865,"remaining_time":0.5540883337},
{"learn":[3.76116362],"iteration":570,"passed_time":0.7354187752,"remaining_time":0.552530043},
{"learn":[3.758633056],"iteration":571,"passed_time":0.736348925,"remaining_time":0.5509743705},
{"learn":[3.754603809],"iteration":572,"passed_time":0.7371950014,"remaining_time":0.5493582297},
{"learn":[3.754070549],"iteration":573,"passed_time":0.7380707125,"remaining_time":0.5477667657},
{"learn":[3.750534319],"iteration":574,"passed_time":0.7391615731,"remaining_time":0.5463368149},
{"learn":[3.746491516],"iteration":575,"passed_time":0.7399979283,"remaining_time":0.5447206972},
{"learn":[3.744210544],"iteration":576,"passed_time":0.7408613826,"remaining_time":0.5431271488},
{"learn":[3.742929991],"iteration":577,"passed_time":0.7416674818,"remaining_time":0.5414942514},
{"learn":[3.740402992],"iteration":578,"passed_time":0.7426189777,"remaining_time":0.5399699302},
{"learn":[3.739644243],"iteration":579,"passed_time":0.7436510184,"remaining_time":0.5385059099},
{"learn":[3.737529404],"iteration":580,"passed_time":0.7446578757,"remaining_time":0.537025215},
{"learn":[3.737196923],"iteration":581,"passed_time":0.7457635782,"remaining_time":0.5356171403},
{"learn":[3.733954464],"iteration":582,"passed_time":0.7467768389,"remaining_time":0.5341439826},
{"learn":[3.731608623],"iteration":583,"passed_time":0.7476210107,"remaining_time":0.5325519528},
{"learn":[3.729843952],"iteration":584,"passed_time":0.7484843242,"remaining_time":0.530976059},
{"learn":[3.727223798],"iteration":585,"passed_time":0.7493112989,"remaining_time":0.5293769245},
{"learn":[3.725351667],"iteration":586,"passed_time":0.7501377224,"remaining_time":0.527780033},
{"learn":[3.725026912],"iteration":587,"passed_time":0.7509604478,"remaining_time":0.5261831709},
{"learn":[3.721974565],"iteration":588,"passed_time":0.7519331706,"remaining_time":0.5246936046},
{"learn":[3.720269493],"iteration":589,"passed_time":0.7529036289,"remaining_time":0.5232042167},
{"learn":[3.718907466],"iteration":590,"passed_time":0.7539305099,"remaining_time":0.5217556321},
{"learn":[3.715602912],"iteration":591,"passed_time":0.7551161874,"remaining_time":0.5204179129},
{"learn":[3.714463059],"iteration":592,"passed_time":0.7561863824,"remaining_time":0.5190014463},
{"learn":[3.710802077],"iteration":593,"passed_time":0.7573185732,"remaining_time":0.5176285197},
{"learn":[3.708032435],"iteration":594,"passed_time":0.7585240043,"remaining_time":0.516306255},
{"learn":[3.703788939],"iteration":595,"passed_time":0.7597419292,"remaining_time":0.5149928513},
{"learn":[3.702500944],"iteration":596,"passed_time":0.7608193299,"remaining_time":0.5135849078},
{"learn":[3.698196925],"iteration":597,"passed_time":0.7621641041,"remaining_time":0.5123578091},
{"learn":[3.69658891],"iteration":598,"passed_time":0.7633486291,"remaining_time":0.5110230388},
{"learn":[3.696124066],"iteration":599,"passed_time":0.7643474989,"remaining_time":0.5095649993},
{"learn":[3.693537052],"iteration":600,"passed_time":0.7657063343,"remaining_time":0.5083474666},
{"learn":[3.691343275],"iteration":601,"passed_time":0.7667529589,"remaining_time":0.5069230526},
{"learn":[3.690973831],"iteration":602,"passed_time":0.7678481389,"remaining_time":0.5055318593},
{"learn":[3.686151073],"iteration":603,"passed_time":0.7690606349,"remaining_time":0.504218562},
{"learn":[3.683921982],"iteration":604,"passed_time":0.7701679915,"remaining_time":0.5028369531},
{"learn":[3.679975271],"iteration":605,"passed_time":0.7713496773,"remaining_time":0.5015045757},
{"learn":[3.674047638],"iteration":606,"passed_time":0.7723918211,"remaining_time":0.5000823487},
{"learn":[3.673151794],"iteration":607,"passed_time":0.7733838655,"remaining_time":0.4986290712},
{"learn":[3.670953108],"iteration":608,"passed_time":0.7743382683,"remaining_time":0.4971531411},
{"learn":[3.6703947],"iteration":609,"passed_time":0.7751804162,"remaining_time":0.4956071513},
{"learn":[3.668433805],"iteration":610,"passed_time":0.7761391384,"remaining_time":0.4941376838},
{"learn":[3.668304956],"iteration":611,"passed_time":0.7770918375,"remaining_time":0.4926660669},
{"learn":[3.667880012],"iteration":612,"passed_time":0.7780715455,"remaining_time":0.4912131943},
{"learn":[3.667282264],"iteration":613,"passed_time":0.7790066361,"remaining_time":0.4897338136},
{"learn":[3.664611483],"iteration":614,"passed_time":0.779893271,"remaining_time":0.4882258689},
{"learn":[3.662543394],"iteration":615,"passed_time":0.7808662243,"remaining_time":0.4867737502},
{"learn":[3.659041959],"iteration":616,"passed_time":0.781817159,"remaining_time":0.4853095169},
{"learn":[3.656868545],"iteration":617,"passed_time":0.7829848067,"remaining_time":0.4839808999},
{"learn":[3.654785614],"iteration":618,"passed_time":0.7842984465,"remaining_time":0.4827426625},
{"learn":[3.654566096],"iteration":619,"passed_time":0.7852353411,"remaining_time":0.4812732736},
{"learn":[3.651007045],"iteration":620,"passed_time":0.7863225542,"remaining_time":0.4798973398},
{"learn":[3.648921786],"iteration":621,"passed_time":0.7874567298,"remaining_time":0.4785508744},
{"learn":[3.647655706],"iteration":622,"passed_time":0.7885287793,"remaining_time":0.4771674957},
{"learn":[3.647241144],"iteration":623,"passed_time":0.7894750243,"remaining_time":0.4757093095},
{"learn":[3.644195689],"iteration":624,"passed_time":0.7904094736,"remaining_time":0.4742456842},
{"learn":[3.642632246],"iteration":625,"passed_time":0.7914290085,"remaining_time":0.4728345834},
{"learn":[3.642523322],"iteration":626,"passed_time":0.7922051919,"remaining_time":0.4712799626},
{"learn":[3.641494659],"iteration":627,"passed_time":0.7931625116,"remaining_time":0.4698351183},
{"learn":[3.63976496],"iteration":628,"passed_time":0.7940783101,"remaining_time":0.4683673339},
{"learn":[3.637945652],"iteration":629,"passed_time":0.7949821626,"remaining_time":0.466894286},
{"learn":[3.636233667],"iteration":630,"passed_time":0.7963299333,"remaining_time":0.4656826393},
{"learn":[3.635304404],"iteration":631,"passed_time":0.7973897757,"remaining_time":0.4643029074},
{"learn":[3.632234951],"iteration":632,"passed_time":0.7984180953,"remaining_time":0.4629059099},
{"learn":[3.631630987],"iteration":633,"passed_time":0.7994775724,"remaining_time":0.4615280623},
{"learn":[3.630301009],"iteration":634,"passed_time":0.800818629,"remaining_time":0.4603130702},
{"learn":[3.629077964],"iteration":635,"passed_time":0.8017803578,"remaining_time":0.4588805821},
{"learn":[3.628004522],"iteration":636,"passed_time":0.8026709413,"remaining_time":0.4574090294},
{"learn":[3.625062876],"iteration":637,"passed_time":0.8035405892,"remaining_time":0.4559274189},
{"learn":[3.624917986],"iteration":638,"passed_time":0.8044168815,"remaining_time":0.4544514777},
{"learn":[3.622887087],"iteration":639,"passed_time":0.8054425593,"remaining_time":0.4530614396},
{"learn":[3.621220865],"iteration":640,"passed_time":0.8063234818,"remaining_time":0.4515914664},
{"learn":[3.621143844],"iteration":641,"passed_time":0.8071466582,"remaining_time":0.4500911272},
{"learn":[3.620822821],"iteration":642,"passed_time":0.8080403184,"remaining_time":0.4486320275},
{"learn":[3.619202826],"iteration":643,"passed_time":0.8093572724,"remaining_time":0.4474086786},
{"learn":[3.618204882],"iteration":644,"passed_time":0.8104357355,"remaining_time":0.4460537769},
{"learn":[3.614259666],"iteration":645,"passed_time":0.8113239137,"remaining_time":0.4445954574},
{"learn":[3.613415661],"iteration":646,"passed_time":0.8122171736,"remaining_time":0.4431416728},
{"learn":[3.611096773],"iteration":647,"passed_time":0.8131217081,"remaining_time":0.4416957427},
{"learn":[3.610820695],"iteration":648,"passed_time":0.8139975895,"remaining_time":0.4402359845},
{"learn":[3.609290065],"iteration":649,"passed_time":0.8149938737,"remaining_time":0.4388428551},
{"learn":[3.60897947],"iteration":650,"passed_time":0.8159233621,"remaining_time":0.4374151358},
{"learn":[3.606570702],"iteration":651,"passed_time":0.8168421572,"remaining_time":0.4359832373},
{"learn":[3.606292637],"iteration":652,"passed_time":0.8177413195,"remaining_time":0.4345424776},
{"learn":[3.602753838],"iteration":653,"passed_time":0.8186085515,"remaining_time":0.4330864814},
{"learn":[3.599755869],"iteration":654,"passed_time":0.8196772934,"remaining_time":0.4317384217},
{"learn":[3.599509575],"iteration":655,"passed_time":0.8206057896,"remaining_time":0.4303176702},
{"learn":[3.595337722],"iteration":656,"passed_time":0.8218229243,"remaining_time":0.4290491066},
{"learn":[3.595168561],"iteration":657,"passed_time":0.8228792991,"remaining_time":0.4276971433},
{"learn":[3.59290559],"iteration":658,"passed_time":0.8238384919,"remaining_time":0.4262957902},
{"learn":[3.592015928],"iteration":659,"passed_time":0.8248335439,"remaining_time":0.4249142499},
{"learn":[3.590680403],"iteration":660,"passed_time":0.8257674514,"remaining_time":0.4235025205},
{"learn":[3.590361532],"iteration":661,"passed_time":0.8266771767,"remaining_time":0.4220798878},
{"learn":[3.589069739],"iteration":662,"passed_time":0.827616466,"remaining_time":0.4206738297},
{"learn":[3.585010186],"iteration":663,"passed_time":0.8287196535,"remaining_time":0.4193521138},
{"learn":[3.582997552],"iteration":664,"passed_time":0.8296558867,"remaining_time":0.4179469504},
{"learn":[3.582119256],"iteration":665,"passed_time":0.830545919,"remaining_time":0.4165200254},
{"learn":[3.579019356],"iteration":666,"passed_time":0.8314111071,"remaining_time":0.4150823068},
{"learn":[3.57719559],"iteration":667,"passed_time":0.8322908064,"remaining_time":0.4136535145},
{"learn":[3.574050046],"iteration":668,"passed_time":0.8331302483,"remaining_time":0.4122064457},
{"learn":[3.572204518],"iteration":669,"passed_time":0.8342293569,"remaining_time":0.4108890862},
{"learn":[3.569508025],"iteration":670,"passed_time":0.8352418464,"remaining_time":0.4095299068},
{"learn":[3.566268704],"iteration":671,"passed_time":0.8362155719,"remaining_time":0.4081528387},
{"learn":[3.562564052],"iteration":672,"passed_time":0.8371424045,"remaining_time":0.4067541847},
{"learn":[3.561173586],"iteration":673,"passed_time":0.8380506466,"remaining_time":0.4053479389},
{"learn":[3.559551904],"iteration":674,"passed_time":0.8393049338,"remaining_time":0.404109783},
{"learn":[3.558593054],"iteration":675,"passed_time":0.8402866467,"remaining_time":0.4027409372},
{"learn":[3.555647008],"iteration":676,"passed_time":0.8411926439,"remaining_time":0.4013371107},
{"learn":[3.553100059],"iteration":677,"passed_time":0.842071131,"remaining_time":0.3999216876},
{"learn":[3.55085578],"iteration":678,"passed_time":0.8430104304,"remaining_time":0.3985365952},
{"learn":[3.550737965],"iteration":679,"passed_time":0.8440019441,"remaining_time":0.3971773855},
{"learn":[3.549408772],"iteration":680,"passed_time":0.8449722316,"remaining_time":0.3958093126},
{"learn":[3.547390589],"iteration":681,"passed_time":0.8458846924,"remaining_time":0.3944154431},
{"learn":[3.54723575],"iteration":682,"passed_time":0.8470322767,"remaining_time":0.3931321109},
{"learn":[3.543988891],"iteration":683,"passed_time":0.8482951833,"remaining_time":0.3919024531},
{"learn":[3.543868508],"iteration":684,"passed_time":0.8493071417,"remaining_time":0.3905572987},
{"learn":[3.542752124],"iteration":685,"passed_time":0.8502112542,"remaining_time":0.3891637519},
{"learn":[3.541334315],"iteration":686,"passed_time":0.8511278646,"remaining_time":0.387777324},
{"learn":[3.540208266],"iteration":687,"passed_time":0.8521035939,"remaining_time":0.3864190717},
{"learn":[3.537730983],"iteration":688,"passed_time":0.8530895551,"remaining_time":0.3850665481},
{"learn":[3.53419867],"iteration":689,"passed_time":0.8542208238,"remaining_time":0.3837803701},
{"learn":[3.532628335],"iteration":690,"passed_time":0.855147446,"remaining_time":0.3824031271},
{"learn":[3.532204987],"iteration":691,"passed_time":0.8560344217,"remaining_time":0.3810095403},
{"learn":[3.530618147],"iteration":692,"passed_time":0.8569197938,"remaining_time":0.3796167052},
{"learn":[3.528909306],"iteration":693,"passed_time":0.8581010116,"remaining_time":0.3783557774},
{"learn":[3.526700678],"iteration":694,"passed_time":0.8591607242,"remaining_time":0.3770417567},
{"learn":[3.526439574],"iteration":695,"passed_time":0.8602407516,"remaining_time":0.3757373398},
{"learn":[3.525784216],"iteration":696,"passed_time":0.861302619,"remaining_time":0.3744256722},
{"learn":[3.524112693],"iteration":697,"passed_time":0.8622698698,"remaining_time":0.3730737832},
{"learn":[3.522813541],"iteration":698,"passed_time":0.8632472021,"remaining_time":0.371727336},
{"learn":[3.519148203],"iteration":699,"passed_time":0.8641753777,"remaining_time":0.3703608762},
{"learn":[3.517236747],"iteration":700,"passed_time":0.8650542552,"remaining_time":0.3689746395},
{"learn":[3.515603888],"iteration":701,"passed_time":0.8660612377,"remaining_time":0.3676442291},
{"learn":[3.51263524],"iteration":702,"passed_time":0.8669955166,"remaining_time":0.3662840234},
{"learn":[3.51123442],"iteration":703,"passed_time":0.8678384757,"remaining_time":0.3648866318},
{"learn":[3.50828027],"iteration":704,"passed_time":0.8688548136,"remaining_time":0.3635633617},
{"learn":[3.508265537],"iteration":705,"passed_time":0.8694358917,"remaining_time":0.3620597056},
{"learn":[3.506774876],"iteration":706,"passed_time":0.8704679335,"remaining_time":0.3607455509},
{"learn":[3.50552068],"iteration":707,"passed_time":0.8714792219,"remaining_time":0.3594236339},
{"learn":[3.501973993],"iteration":708,"passed_time":0.8727722537,"remaining_time":0.3582182311},
{"learn":[3.498880354],"iteration":709,"passed_time":0.874048549,"remaining_time":0.3570057453},
{"learn":[3.497370959],"iteration":710,"passed_time":0.8750176233,"remaining_time":0.3556682041},
{"learn":[3.496050455],"iteration":711,"passed_time":0.8760552276,"remaining_time":0.3543594179},
{"learn":[3.495630067],"iteration":712,"passed_time":0.8770117751,"remaining_time":0.353018765},
{"learn":[3.49550669],"iteration":713,"passed_time":0.8779747371,"remaining_time":0.3516817574},
{"learn":[3.493652375],"iteration":714,"passed_time":0.8790490516,"remaining_time":0.3503901814},
{"learn":[3.491915684],"iteration":715,"passed_time":0.8800120331,"remaining_time":0.3490550522},
{"learn":[3.490303956],"iteration":716,"passed_time":0.8809118668,"remaining_time":0.3476960367},
{"learn":[3.488363853],"iteration":717,"passed_time":0.8818946515,"remaining_time":0.3463708799},
{"learn":[3.485483936],"iteration":718,"passed_time":0.8828263748,"remaining_time":0.3450267195},
{"learn":[3.483763466],"iteration":719,"passed_time":0.8839577138,"remaining_time":0.3437613331},
{"learn":[3.481642352],"iteration":720,"passed_time":0.8851383798,"remaining_time":0.3425154063},
{"learn":[3.479826119],"iteration":721,"passed_time":0.8864697553,"remaining_time":0.3413276897},
{"learn":[3.478588728],"iteration":722,"passed_time":0.8874649972,"remaining_time":0.3400107942},
{"learn":[3.475390887],"iteration":723,"passed_time":0.8885034339,"remaining_time":0.3387112538},
{"learn":[3.472636852],"iteration":724,"passed_time":0.8895829893,"remaining_time":0.3374280304},
{"learn":[3.47061883],"iteration":725,"passed_time":0.8907121535,"remaining_time":0.336164091},
{"learn":[3.46953149],"iteration":726,"passed_time":0.8916896667,"remaining_time":0.334843575},
{"learn":[3.467217162],"iteration":727,"passed_time":0.8938569384,"remaining_time":0.3339685264},
{"learn":[3.465686216],"iteration":728,"passed_time":0.8951596212,"remaining_time":0.3327685286},
{"learn":[3.462631216],"iteration":729,"passed_time":0.896430404,"remaining_time":0.3315564508},
{"learn":[3.461451053],"iteration":730,"passed_time":0.8976540939,"remaining_time":0.3303268827},
{"learn":[3.458950469],"iteration":731,"passed_time":0.8992493252,"remaining_time":0.3292333595},
{"learn":[3.458072145],"iteration":732,"passed_time":0.9004453523,"remaining_time":0.3279930547},
{"learn":[3.454364268],"iteration":733,"passed_time":0.9023775986,"remaining_time":0.3270196747},
{"learn":[3.453243406],"iteration":734,"passed_time":0.9037015182,"remaining_time":0.3258243569},
{"learn":[3.453017963],"iteration":735,"passed_time":0.9049678668,"remaining_time":0.3246080392},
{"learn":[3.45201581],"iteration":736,"passed_time":0.9061503488,"remaining_time":0.3233616577},
{"learn":[3.449510107],"iteration":737,"passed_time":0.9074781665,"remaining_time":0.3221670456},
{"learn":[3.447189189],"iteration":738,"passed_time":0.9086486409,"remaining_time":0.3209165024},
{"learn":[3.446423605],"iteration":739,"passed_time":0.909689123,"remaining_time":0.3196205027},
{"learn":[3.445531987],"iteration":740,"passed_time":0.9119397866,"remaining_time":0.3187481845},
{"learn":[3.445328199],"iteration":741,"passed_time":0.913309369,"remaining_time":0.3175657914},
{"learn":[3.443327544],"iteration":742,"passed_time":0.91452413,"remaining_time":0.3163293424},
{"learn":[3.441475798],"iteration":743,"passed_time":0.9156957974,"remaining_time":0.3150781238},
{"learn":[3.439046501],"iteration":744,"passed_time":0.9167539065,"remaining_time":0.3137882499},
{"learn":[3.435899469],"iteration":745,"passed_time":0.918028027,"remaining_time":0.3125725454},
{"learn":[3.433988352],"iteration":746,"passed_time":0.9193303772,"remaining_time":0.3113662455},
{"learn":[3.433413263],"iteration":747,"passed_time":0.9204901787,"remaining_time":0.3101116645},
{"learn":[3.429944699],"iteration":748,"passed_time":0.9215235634,"remaining_time":0.3088149725},
{"learn":[3.429291634],"iteration":749,"passed_time":0.9233062192,"remaining_time":0.3077687397},
{"learn":[3.429175603],"iteration":750,"passed_time":0.9244150289,"remaining_time":0.3064971268},
{"learn":[3.428780323],"iteration":751,"passed_time":0.9254791597,"remaining_time":0.3052112122},
{"learn":[3.423893341],"iteration":752,"passed_time":0.9268032427,"remaining_time":0.3040111566},
{"learn":[3.421024316],"iteration":753,"passed_time":0.9282743231,"remaining_time":0.3028587314},
{"learn":[3.420969872],"iteration":754,"passed_time":0.929234298,"remaining_time":0.3015396066},
{"learn":[3.419544785],"iteration":755,"passed_time":0.930454995,"remaining_time":0.3003055804},
{"learn":[3.417057977],"iteration":756,"passed_time":0.9326683402,"remaining_time":0.2993902334},
{"learn":[3.415160245],"iteration":757,"passed_time":0.93380008,"remaining_time":0.2981261469},
{"learn":[3.412854597],"iteration":758,"passed_time":0.9348951096,"remaining_time":0.2968507529},
{"learn":[3.410926347],"iteration":759,"passed_time":0.9369994419,"remaining_time":0.2958945606},
{"learn":[3.408963843],"iteration":760,"passed_time":0.9385330988,"remaining_time":0.2947561243},
{"learn":[3.407629634],"iteration":761,"passed_time":0.9395698914,"remaining_time":0.2934614622},
{"learn":[3.404384724],"iteration":762,"passed_time":0.9407162531,"remaining_time":0.2922015098},
{"learn":[3.403041656],"iteration":763,"passed_time":0.9417374617,"remaining_time":0.290903195},
{"learn":[3.401101731],"iteration":764,"passed_time":0.9429437943,"remaining_time":0.2896624728},
{"learn":[3.400890668],"iteration":765,"passed_time":0.944066778,"remaining_time":0.2883963787},
{"learn":[3.399289941],"iteration":766,"passed_time":0.9450781055,"remaining_time":0.2870967387},
{"learn":[3.399202366],"iteration":767,"passed_time":0.9459470513,"remaining_time":0.2857548384},
{"learn":[3.397447845],"iteration":768,"passed_time":0.9471901141,"remaining_time":0.2845265492},
{"learn":[3.394655341],"iteration":769,"passed_time":0.9485570376,"remaining_time":0.283335219},
{"learn":[3.393228229],"iteration":770,"passed_time":0.9499005626,"remaining_time":0.2821364836},
{"learn":[3.389691197],"iteration":771,"passed_time":0.9509827548,"remaining_time":0.2808601918},
{"learn":[3.389626772],"iteration":772,"passed_time":0.951990754,"remaining_time":0.2795626147},
{"learn":[3.388480222],"iteration":773,"passed_time":0.9529853646,"remaining_time":0.2782618765},
{"learn":[3.388215066],"iteration":774,"passed_time":0.953898838,"remaining_time":0.2769383723},
{"learn":[3.386324358],"iteration":775,"passed_time":0.9548310429,"remaining_time":0.275621332},
{"learn":[3.383913061],"iteration":776,"passed_time":0.9557520333,"remaining_time":0.2743020636},
{"learn":[3.382839768],"iteration":777,"passed_time":0.9569204932,"remaining_time":0.2730544338},
{"learn":[3.381961844],"iteration":778,"passed_time":0.9579216781,"remaining_time":0.2717595518},
{"learn":[3.381521703],"iteration":779,"passed_time":0.9587981709,"remaining_time":0.2704302533},
{"learn":[3.380918963],"iteration":780,"passed_time":0.9596862585,"remaining_time":0.2691053657},
{"learn":[3.377139006],"iteration":781,"passed_time":0.9606773313,"remaining_time":0.2678103046},
{"learn":[3.376004372],"iteration":782,"passed_time":0.9623360311,"remaining_time":0.2667010456},
{"learn":[3.373826468],"iteration":783,"passed_time":0.9636924111,"remaining_time":0.2655070929},
{"learn":[3.373546786],"iteration":784,"passed_time":0.9647884024,"remaining_time":0.2642414096},
{"learn":[3.372109181],"iteration":785,"passed_time":0.9659115635,"remaining_time":0.2629835554},
{"learn":[3.370764924],"iteration":786,"passed_time":0.966981989,"remaining_time":0.2617117708},
{"learn":[3.367833107],"iteration":787,"passed_time":0.9680106939,"remaining_time":0.260429273},
{"learn":[3.36450404],"iteration":788,"passed_time":0.9690632309,"remaining_time":0.2591537918},
{"learn":[3.361794558],"iteration":789,"passed_time":0.9701010256,"remaining_time":0.2578749562},
{"learn":[3.356880529],"iteration":790,"passed_time":0.9711169527,"remaining_time":0.2565909521},
{"learn":[3.353843509],"iteration":791,"passed_time":0.9722157601,"remaining_time":0.2553293916},
{"learn":[3.353640253],"iteration":792,"passed_time":0.9735888361,"remaining_time":0.2541398349},
{"learn":[3.353055088],"iteration":793,"passed_time":0.9751632018,"remaining_time":0.2530020398},
{"learn":[3.351415617],"iteration":794,"passed_time":0.9762620298,"remaining_time":0.2517405234},
{"learn":[3.349169061],"iteration":795,"passed_time":0.9775073971,"remaining_time":0.2505169711},
{"learn":[3.346211014],"iteration":796,"passed_time":0.9785924751,"remaining_time":0.2492525376},
{"learn":[3.344560452],"iteration":797,"passed_time":0.9796199974,"remaining_time":0.2479739843},
{"learn":[3.344445461],"iteration":798,"passed_time":0.9806678642,"remaining_time":0.2467011774},
{"learn":[3.342608898],"iteration":799,"passed_time":0.9820545905,"remaining_time":0.2455136476},
{"learn":[3.339572899],"iteration":800,"passed_time":0.9834017804,"remaining_time":0.2443157981},
{"learn":[3.339309302],"iteration":801,"passed_time":0.9846778352,"remaining_time":0.2431000142},
{"learn":[3.33698088],"iteration":802,"passed_time":0.9869175935,"remaining_time":0.2421205055},
{"learn":[3.334746342],"iteration":803,"passed_time":0.9881617486,"remaining_time":0.2408951527},
{"learn":[3.332048511],"iteration":804,"passed_time":0.9895713242,"remaining_time":0.2397098239},
{"learn":[3.331932544],"iteration":805,"passed_time":0.9906669352,"remaining_time":0.238448369},
{"learn":[3.330541133],"iteration":806,"passed_time":0.9918334614,"remaining_time":0.2372042851},
{"learn":[3.329124989],"iteration":807,"passed_time":0.9931215725,"remaining_time":0.2359892845},
{"learn":[3.32583918],"iteration":808,"passed_time":0.994172778,"remaining_time":0.2347181713},
{"learn":[3.325287299],"iteration":809,"passed_time":0.9951343364,"remaining_time":0.2334265727},
{"learn":[3.322745162],"iteration":810,"passed_time":0.996152348,"remaining_time":0.2321489442},
{"learn":[3.319733662],"iteration":811,"passed_time":0.9974889444,"remaining_time":0.2309457162},
{"learn":[3.318080007],"iteration":812,"passed_time":1.000853998,"remaining_time":0.2302087302},
{"learn":[3.317179538],"iteration":813,"passed_time":1.002158616,"remaining_time":0.2289944748},
{"learn":[3.315685949],"iteration":814,"passed_time":1.003334271,"remaining_time":0.2277507241},
{"learn":[3.314944576],"iteration":815,"passed_time":1.004600354,"remaining_time":0.2265275308},
{"learn":[3.312369052],"iteration":816,"passed_time":1.005926718,"remaining_time":0.2253177349},
{"learn":[3.312321621],"iteration":817,"passed_time":1.006812883,"remaining_time":0.2240097123},
{"learn":[3.309465776],"iteration":818,"passed_time":1.008178613,"remaining_time":0.2228087045},
{"learn":[3.308307377],"iteration":819,"passed_time":1.009271058,"remaining_time":0.2215473053},
{"learn":[3.308076804],"iteration":820,"passed_time":1.010497453,"remaining_time":0.2203155227},
{"learn":[3.305643326],"iteration":821,"passed_time":1.011766804,"remaining_time":0.2190930549},
{"learn":[3.304154814],"iteration":822,"passed_time":1.012871174,"remaining_time":0.2178349913},
{"learn":[3.303076321],"iteration":823,"passed_time":1.013977388,"remaining_time":0.2165776946},
{"learn":[3.301746372],"iteration":824,"passed_time":1.015332297,"remaining_time":0.2153735174},
{"learn":[3.301345455],"iteration":825,"passed_time":1.016497229,"remaining_time":0.2141289563},
{"learn":[3.299181039],"iteration":826,"passed_time":1.017542412,"remaining_time":0.2128595371},
{"learn":[3.297989357],"iteration":827,"passed_time":1.018493749,"remaining_time":0.2115711653},
{"learn":[3.294775182],"iteration":828,"passed_time":1.019524168,"remaining_time":0.2102999189},
{"learn":[3.293840636],"iteration":829,"passed_time":1.02061111,"remaining_time":0.2090408299},
{"learn":[3.289279397],"iteration":830,"passed_time":1.021714498,"remaining_time":0.2077854997},
{"learn":[3.286204979],"iteration":831,"passed_time":1.023189502,"remaining_time":0.2066055725},
{"learn":[3.284833593],"iteration":832,"passed_time":1.024299243,"remaining_time":0.205351709},
{"learn":[3.283519914],"iteration":833,"passed_time":1.025291909,"remaining_time":0.2040748883},
{"learn":[3.282853026],"iteration":834,"passed_time":1.026434412,"remaining_time":0.2028283569},
{"learn":[3.281944673],"iteration":835,"passed_time":1.027730671,"remaining_time":0.2016122369},
{"learn":[3.279764865],"iteration":836,"passed_time":1.02892624,"remaining_time":0.2003763168},
{"learn":[3.277468839],"iteration":837,"passed_time":1.029950617,"remaining_time":0.1991073985},
{"learn":[3.277124974],"iteration":838,"passed_time":1.031180461,"remaining_time":0.1978784913},
{"learn":[3.275636037],"iteration":839,"passed_time":1.032188038,"remaining_time":0.1966072454},
{"learn":[3.274413635],"iteration":840,"passed_time":1.033162114,"remaining_time":0.1953302927},
{"learn":[3.272636087],"iteration":841,"passed_time":1.034162457,"remaining_time":0.1940589884},
{"learn":[3.269644466],"iteration":842,"passed_time":1.035628486,"remaining_time":0.1928750562},
{"learn":[3.26852083],"iteration":843,"passed_time":1.036847787,"remaining_time":0.1916448517},
{"learn":[3.267820927],"iteration":844,"passed_time":1.038017162,"remaining_time":0.190405515},
{"learn":[3.267331099],"iteration":845,"passed_time":1.039108704,"remaining_time":0.1891521755},
{"learn":[3.267231014],"iteration":846,"passed_time":1.040360363,"remaining_time":0.1879281411},
{"learn":[3.267158695],"iteration":847,"passed_time":1.041387134,"remaining_time":0.1866637315},
{"learn":[3.264718705],"iteration":848,"passed_time":1.042482153,"remaining_time":0.1854120202},
{"learn":[3.261678512],"iteration":849,"passed_time":1.043608451,"remaining_time":0.1841661973},
{"learn":[3.261368381],"iteration":850,"passed_time":1.044659314,"remaining_time":0.1829074475},
{"learn":[3.260128799],"iteration":851,"passed_time":1.045727466,"remaining_time":0.1816521888},
{"learn":[3.258972952],"iteration":852,"passed_time":1.047029196,"remaining_time":0.1804376223},
{"learn":[3.258724846],"iteration":853,"passed_time":1.048354509,"remaining_time":0.1792268832},
{"learn":[3.25686724],"iteration":854,"passed_time":1.049691466,"remaining_time":0.178017851},
{"learn":[3.255750259],"iteration":855,"passed_time":1.051125678,"remaining_time":0.1768248803},
{"learn":[3.254915866],"iteration":856,"passed_time":1.052350631,"remaining_time":0.1755964296},
{"learn":[3.254348625],"iteration":857,"passed_time":1.053438374,"remaining_time":0.1743452787},
{"learn":[3.253408514],"iteration":858,"passed_time":1.054579283,"remaining_time":0.1731032351},
{"learn":[3.253291714],"iteration":859,"passed_time":1.055916742,"remaining_time":0.1718934231},
{"learn":[3.250186342],"iteration":860,"passed_time":1.056943673,"remaining_time":0.1706331829},
{"learn":[3.249141318],"iteration":861,"passed_time":1.05789996,"remaining_time":0.1693621745},
{"learn":[3.246300388],"iteration":862,"passed_time":1.058899832,"remaining_time":0.1680988145},
{"learn":[3.245205135],"iteration":863,"passed_time":1.060128142,"remaining_time":0.1668720224},
{"learn":[3.244403535],"iteration":864,"passed_time":1.061511882,"remaining_time":0.1656694845},
{"learn":[3.244211781],"iteration":865,"passed_time":1.062535361,"remaining_time":0.1644107833},
{"learn":[3.242286347],"iteration":866,"passed_time":1.063445367,"remaining_time":0.1631352178},
{"learn":[3.239606746],"iteration":867,"passed_time":1.064362498,"remaining_time":0.1618615781},
{"learn":[3.236773361],"iteration":868,"passed_time":1.065351226,"remaining_time":0.1605995518},
{"learn":[3.234552446],"iteration":869,"passed_time":1.066273659,"remaining_time":0.1593282478},
{"learn":[3.233724647],"iteration":870,"passed_time":1.067379502,"remaining_time":0.158084909},
{"learn":[3.230851485],"iteration":871,"passed_time":1.068362628,"remaining_time":0.156823872},
{"learn":[3.227728941],"iteration":872,"passed_time":1.069310627,"remaining_time":0.1555583615},
{"learn":[3.225787575],"iteration":873,"passed_time":1.070267635,"remaining_time":0.1542948765},
{"learn":[3.222797487],"iteration":874,"passed_time":1.071162849,"remaining_time":0.1530232641},
{"learn":[3.22137014],"iteration":875,"passed_time":1.072065138,"remaining_time":0.1517535127},
{"learn":[3.219701963],"iteration":876,"passed_time":1.073132156,"remaining_time":0.1505077027},
{"learn":[3.21783327],"iteration":877,"passed_time":1.074340173,"remaining_time":0.1492818919},
{"learn":[3.217713355],"iteration":878,"passed_time":1.075477074,"remaining_time":0.1480463321},
{"learn":[3.217666091],"iteration":879,"passed_time":1.076367456,"remaining_time":0.1467773804},
{"learn":[3.214962005],"iteration":880,"passed_time":1.077268523,"remaining_time":0.1455107312},
{"learn":[3.214081828],"iteration":881,"passed_time":1.078204114,"remaining_time":0.14424953},
{"learn":[3.213358337],"iteration":882,"passed_time":1.07906397,"remaining_time":0.1429790312},
{"learn":[3.210850401],"iteration":883,"passed_time":1.080158389,"remaining_time":0.1417402411},
{"learn":[3.207810328],"iteration":884,"passed_time":1.081110095,"remaining_time":0.1404832327},
{"learn":[3.204935073],"iteration":885,"passed_time":1.082013036,"remaining_time":0.1392206389},
{"learn":[3.20280198],"iteration":886,"passed_time":1.082875017,"remaining_time":0.137953638},
{"learn":[3.200663495],"iteration":887,"passed_time":1.083820129,"remaining_time":0.1366980343},
{"learn":[3.197301669],"iteration":888,"passed_time":1.084806392,"remaining_time":0.1354482672},
{"learn":[3.195666943],"iteration":889,"passed_time":1.085788064,"remaining_time":0.1341985248},
{"learn":[3.193886506],"iteration":890,"passed_time":1.086958073,"remaining_time":0.1329724242},
{"learn":[3.190601248],"iteration":891,"passed_time":1.08792364,"remaining_time":0.1317216963},
{"learn":[3.188983797],"iteration":892,"passed_time":1.088929625,"remaining_time":0.1304764501},
{"learn":[3.187365749],"iteration":893,"passed_time":1.08990368,"remaining_time":0.1292279532},
{"learn":[3.186160771],"iteration":894,"passed_time":1.090765902,"remaining_time":0.1279669494},
{"learn":[3.185358981],"iteration":895,"passed_time":1.091551547,"remaining_time":0.1266979474},
{"learn":[3.183832164],"iteration":896,"passed_time":1.092419921,"remaining_time":0.1254395227},
{"learn":[3.183106966],"iteration":897,"passed_time":1.093285279,"remaining_time":0.1241816241},
{"learn":[3.182838152],"iteration":898,"passed_time":1.094279459,"remaining_time":0.1229390716},
{"learn":[3.180835453],"iteration":899,"passed_time":1.095157404,"remaining_time":0.121684156},
{"learn":[3.179957348],"iteration":900,"passed_time":1.095982835,"remaining_time":0.1204243071},
{"learn":[3.179752966],"iteration":901,"passed_time":1.096778111,"remaining_time":0.1191621451},
{"learn":[3.178851983],"iteration":902,"passed_time":1.097611169,"remaining_time":0.1179050757},
{"learn":[3.176748586],"iteration":903,"passed_time":1.098591127,"remaining_time":0.1166645445},
{"learn":[3.172960988],"iteration":904,"passed_time":1.099810107,"remaining_time":0.1154496797},
{"learn":[3.172794225],"iteration":905,"passed_time":1.100760721,"remaining_time":0.1142069623},
{"learn":[3.169996507],"iteration":906,"passed_time":1.101641423,"remaining_time":0.1129577204},
{"learn":[3.16813015],"iteration":907,"passed_time":1.102563305,"remaining_time":0.1117134626},
{"learn":[3.166920871],"iteration":908,"passed_time":1.103592762,"remaining_time":0.1104806836},
{"learn":[3.16531606],"iteration":909,"passed_time":1.104535991,"remaining_time":0.1092398232},
{"learn":[3.162035247],"iteration":910,"passed_time":1.105511148,"remaining_time":0.1080027357},
{"learn":[3.16189467],"iteration":911,"passed_time":1.10631412,"remaining_time":0.1067496081},
{"learn":[3.161008416],"iteration":912,"passed_time":1.107162332,"remaining_time":0.1055017775},
{"learn":[3.160560787],"iteration":913,"passed_time":1.107939648,"remaining_time":0.1042481507},
{"learn":[3.160416261],"iteration":914,"passed_time":1.108776955,"remaining_time":0.1030011379},
{"learn":[3.15844291],"iteration":915,"passed_time":1.10963141,"remaining_time":0.1017565922},
{"learn":[3.155040501],"iteration":916,"passed_time":1.110554254,"remaining_time":0.1005190873},
{"learn":[3.154937548],"iteration":917,"passed_time":1.111383022,"remaining_time":0.0992738647},
{"learn":[3.153721161],"iteration":918,"passed_time":1.112585055,"remaining_time":0.09806244768},
{"learn":[3.153170511],"iteration":919,"passed_time":1.113646612,"remaining_time":0.0968388358},
{"learn":[3.153113601],"iteration":920,"passed_time":1.114553932,"remaining_time":0.09560234594},
{"learn":[3.150607379],"iteration":921,"passed_time":1.115430755,"remaining_time":0.09436399014},
{"learn":[3.148408359],"iteration":922,"passed_time":1.116320377,"remaining_time":0.09312748538},
{"learn":[3.147495728],"iteration":923,"passed_time":1.117136778,"remaining_time":0.09188570904},
{"learn":[3.146946235],"iteration":924,"passed_time":1.118011567,"remaining_time":0.09064958654},
{"learn":[3.14472738],"iteration":925,"passed_time":1.118893422,"remaining_time":0.08941480909},
{"learn":[3.144469477],"iteration":926,"passed_time":1.119736101,"remaining_time":0.08817770805},
{"learn":[3.142975516],"iteration":927,"passed_time":1.120554807,"remaining_time":0.08693959713},
{"learn":[3.14079113],"iteration":928,"passed_time":1.121347066,"remaining_time":0.08570036783},
{"learn":[3.138173032],"iteration":929,"passed_time":1.12216896,"remaining_time":0.08446433029},
{"learn":[3.136352813],"iteration":930,"passed_time":1.123210122,"remaining_time":0.08324543329},
{"learn":[3.133735004],"iteration":931,"passed_time":1.124175468,"remaining_time":0.08202138611},
{"learn":[3.1319496],"iteration":932,"passed_time":1.125180772,"remaining_time":0.08080076285},
{"learn":[3.129865343],"iteration":933,"passed_time":1.126182841,"remaining_time":0.07958037203},
{"learn":[3.129830206],"iteration":934,"passed_time":1.126976663,"remaining_time":0.07834597122},
{"learn":[3.126676562],"iteration":935,"passed_time":1.127825946,"remaining_time":0.07711630402},
{"learn":[3.12645665],"iteration":936,"passed_time":1.128779788,"remaining_time":0.0758944788},
{"learn":[3.126378007],"iteration":937,"passed_time":1.129721904,"remaining_time":0.07467244994},
{"learn":[3.124621914],"iteration":938,"passed_time":1.130622809,"remaining_time":0.07344834012},
{"learn":[3.123379018],"iteration":939,"passed_time":1.13168621,"remaining_time":0.07223529001},
{"learn":[3.123332451],"iteration":940,"passed_time":1.132586965,"remaining_time":0.07101236021},
{"learn":[3.122432444],"iteration":941,"passed_time":1.133618877,"remaining_time":0.0697981899},
{"learn":[3.121889006],"iteration":942,"passed_time":1.134526698,"remaining_time":0.06857690542},
{"learn":[3.121070914],"iteration":943,"passed_time":1.135395003,"remaining_time":0.06735394087},
{"learn":[3.118444705],"iteration":944,"passed_time":1.136253687,"remaining_time":0.06613116695},
{"learn":[3.116820458],"iteration":945,"passed_time":1.137201134,"remaining_time":0.06491422963},
{"learn":[3.114971041],"iteration":946,"passed_time":1.13874374,"remaining_time":0.06373117026},
{"learn":[3.114685138],"iteration":947,"passed_time":1.139811851,"remaining_time":0.06252132514},
{"learn":[3.113399363],"iteration":948,"passed_time":1.140739736,"remaining_time":0.06130424291},
{"learn":[3.110575399],"iteration":949,"passed_time":1.141701324,"remaining_time":0.06008954335},
{"learn":[3.110466553],"iteration":950,"passed_time":1.142495908,"remaining_time":0.05886677127},
{"learn":[3.108691641],"iteration":951,"passed_time":1.143352707,"remaining_time":0.05764803567},
{"learn":[3.107898017],"iteration":952,"passed_time":1.14430016,"remaining_time":0.05643453045},
{"learn":[3.105551729],"iteration":953,"passed_time":1.145165899,"remaining_time":0.05521764295},
{"learn":[3.104824945],"iteration":954,"passed_time":1.146131336,"remaining_time":0.05400618862},
{"learn":[3.103186704],"iteration":955,"passed_time":1.147021088,"remaining_time":0.05279176555},
{"learn":[3.102330655],"iteration":956,"passed_time":1.147841699,"remaining_time":0.05157491437},
{"learn":[3.102291298],"iteration":957,"passed_time":1.148615337,"remaining_time":0.05035683106},
{"learn":[3.100363529],"iteration":958,"passed_time":1.149644733,"remaining_time":0.04915060903},
{"learn":[3.097871596],"iteration":959,"passed_time":1.150896856,"remaining_time":0.04795403567},
{"learn":[3.097372213],"iteration":960,"passed_time":1.151960417,"remaining_time":0.04674969435},
{"learn":[3.095981813],"iteration":961,"passed_time":1.152774153,"remaining_time":0.04553577735},
{"learn":[3.095347452],"iteration":962,"passed_time":1.153597941,"remaining_time":0.04432307768},
{"learn":[3.094728409],"iteration":963,"passed_time":1.154540518,"remaining_time":0.04311562099},
{"learn":[3.094118537],"iteration":964,"passed_time":1.155530018,"remaining_time":0.04191041514},
{"learn":[3.093793695],"iteration":965,"passed_time":1.156520801,"remaining_time":0.04070570108},
{"learn":[3.092581602],"iteration":966,"passed_time":1.157391251,"remaining_time":0.03949732293},
{"learn":[3.091694202],"iteration":967,"passed_time":1.15826195,"remaining_time":0.03828965125},
{"learn":[3.090298312],"iteration":968,"passed_time":1.15908202,"remaining_time":0.03708105534},
{"learn":[3.090020107],"iteration":969,"passed_time":1.160015116,"remaining_time":0.03587675618},
{"learn":[3.088949869],"iteration":970,"passed_time":1.160853957,"remaining_time":0.03467020057},
{"learn":[3.086700204],"iteration":971,"passed_time":1.161760305,"remaining_time":0.03346634625},
{"learn":[3.086584317],"iteration":972,"passed_time":1.162710849,"remaining_time":0.03226432984},
{"learn":[3.084850742],"iteration":973,"passed_time":1.163801559,"remaining_time":0.03106657139},
{"learn":[3.084239948],"iteration":974,"passed_time":1.164760291,"remaining_time":0.02986564848},
{"learn":[3.082561673],"iteration":975,"passed_time":1.165602408,"remaining_time":0.0286623543},
{"learn":[3.07991814],"iteration":976,"passed_time":1.166468057,"remaining_time":0.02746035343},
{"learn":[3.079350277],"iteration":977,"passed_time":1.167315315,"remaining_time":0.02625862672},
{"learn":[3.077637462],"iteration":978,"passed_time":1.168169549,"remaining_time":0.02505777379},
{"learn":[3.076733301],"iteration":979,"passed_time":1.169026459,"remaining_time":0.02385768284},
{"learn":[3.07594065],"iteration":980,"passed_time":1.16998884,"remaining_time":0.0226603343},
{"learn":[3.072594655],"iteration":981,"passed_time":1.170906562,"remaining_time":0.02146264575},
{"learn":[3.071977674],"iteration":982,"passed_time":1.171756888,"remaining_time":0.02026436124},
{"learn":[3.069532634],"iteration":983,"passed_time":1.172633601,"remaining_time":0.01906721303},
{"learn":[3.068870784],"iteration":984,"passed_time":1.173444651,"remaining_time":0.0178697155},
{"learn":[3.068801463],"iteration":985,"passed_time":1.174350108,"remaining_time":0.0166743423},
{"learn":[3.067433249],"iteration":986,"passed_time":1.175286741,"remaining_time":0.01547996721},
{"learn":[3.065611456],"iteration":987,"passed_time":1.176359091,"remaining_time":0.01428776224},
{"learn":[3.063039162],"iteration":988,"passed_time":1.177272033,"remaining_time":0.01309402666},
{"learn":[3.06177873],"iteration":989,"passed_time":1.178111425,"remaining_time":0.0119001154},
{"learn":[3.061689148],"iteration":990,"passed_time":1.179024277,"remaining_time":0.01070758677},
{"learn":[3.058984039],"iteration":991,"passed_time":1.180188989,"remaining_time":0.009517653136},
{"learn":[3.057492984],"iteration":992,"passed_time":1.181117615,"remaining_time":0.008326106047},
{"learn":[3.057290731],"iteration":993,"passed_time":1.181977912,"remaining_time":0.007134675527},
{"learn":[3.056068348],"iteration":994,"passed_time":1.182785936,"remaining_time":0.005943647918},
{"learn":[3.054987307],"iteration":995,"passed_time":1.18369059,"remaining_time":0.00475377747},
{"learn":[3.054200234],"iteration":996,"passed_time":1.184484733,"remaining_time":0.003564146639},
{"learn":[3.052732869],"iteration":997,"passed_time":1.185382582,"remaining_time":0.002375516197},
{"learn":[3.051787862],"iteration":998,"passed_time":1.186180023,"remaining_time":0.00118736739},
{"learn":[3.051366222],"iteration":999,"passed_time":1.187013892,"remaining_time":0}
]}